[
  {
    "id": "sy-lesson-001",
    "courseId": "sy-course-01",
    "order": 1,
    "title": "SD课程1章1",
    "slug": "SD课程1章1",
    "summary": "SD课程1章1",
    "content": "# SD课程1章1\n\nSD课程1章1内容。",
    "contentFormat": "markdown",
    "estimatedMinutes": 30,
    "difficulty": "easy",
    "knowledgePointIds": [],
    "practiceQuestionIds": [],
    "tags": [
      "SysDesign"
    ],
    "prerequisites": [],
    "updatedAt": "2026-07-03T00:00:00.000Z"
  },
  {
    "id": "sy-lesson-002",
    "courseId": "sy-course-01",
    "order": 2,
    "title": "SD课程1章2",
    "slug": "SD课程1章2",
    "summary": "SD课程1章2",
    "content": "# SD课程1章2\n\nSD课程1章2内容。",
    "contentFormat": "markdown",
    "estimatedMinutes": 30,
    "difficulty": "easy",
    "knowledgePointIds": [],
    "practiceQuestionIds": [],
    "tags": [
      "SysDesign"
    ],
    "prerequisites": [],
    "updatedAt": "2026-07-03T00:00:00.000Z"
  },
  {
    "id": "sy-lesson-003",
    "courseId": "sy-course-01",
    "order": 3,
    "title": "SD课程1章3",
    "slug": "SD课程1章3",
    "summary": "SD课程1章3",
    "content": "# SD课程1章3\n\nSD课程1章3内容。",
    "contentFormat": "markdown",
    "estimatedMinutes": 30,
    "difficulty": "easy",
    "knowledgePointIds": [],
    "practiceQuestionIds": [],
    "tags": [
      "SysDesign"
    ],
    "prerequisites": [],
    "updatedAt": "2026-07-03T00:00:00.000Z"
  },
  {
    "id": "sy-lesson-004",
    "courseId": "sy-course-01",
    "order": 4,
    "title": "SD课程1章4",
    "slug": "SD课程1章4",
    "summary": "SD课程1章4",
    "content": "# SD课程1章4\n\nSD课程1章4内容。",
    "contentFormat": "markdown",
    "estimatedMinutes": 30,
    "difficulty": "easy",
    "knowledgePointIds": [],
    "practiceQuestionIds": [],
    "tags": [
      "SysDesign"
    ],
    "prerequisites": [],
    "updatedAt": "2026-07-03T00:00:00.000Z"
  },
  {
    "id": "sy-lesson-005",
    "courseId": "sy-course-01",
    "order": 5,
    "title": "SD课程1章5",
    "slug": "SD课程1章5",
    "summary": "SD课程1章5",
    "content": "# SD课程1章5\n\nSD课程1章5内容。",
    "contentFormat": "markdown",
    "estimatedMinutes": 30,
    "difficulty": "easy",
    "knowledgePointIds": [],
    "practiceQuestionIds": [],
    "tags": [
      "SysDesign"
    ],
    "prerequisites": [],
    "updatedAt": "2026-07-03T00:00:00.000Z"
  },
  {
    "id": "sy-lesson-006",
    "courseId": "sy-course-01",
    "order": 6,
    "title": "SD课程1章6",
    "slug": "SD课程1章6",
    "summary": "SD课程1章6",
    "content": "# SD课程1章6\n\nSD课程1章6内容。",
    "contentFormat": "markdown",
    "estimatedMinutes": 30,
    "difficulty": "easy",
    "knowledgePointIds": [],
    "practiceQuestionIds": [],
    "tags": [
      "SysDesign"
    ],
    "prerequisites": [],
    "updatedAt": "2026-07-03T00:00:00.000Z"
  },
  {
    "id": "sy-lesson-007",
    "courseId": "sy-course-01",
    "order": 7,
    "title": "SD课程1章7",
    "slug": "SD课程1章7",
    "summary": "SD课程1章7",
    "content": "# SD课程1章7\n\nSD课程1章7内容。",
    "contentFormat": "markdown",
    "estimatedMinutes": 30,
    "difficulty": "easy",
    "knowledgePointIds": [],
    "practiceQuestionIds": [],
    "tags": [
      "SysDesign"
    ],
    "prerequisites": [],
    "updatedAt": "2026-07-03T00:00:00.000Z"
  },
  {
    "id": "sy-lesson-008",
    "courseId": "sy-course-01",
    "order": 8,
    "title": "SD课程1章8",
    "slug": "SD课程1章8",
    "summary": "SD课程1章8",
    "content": "# SD课程1章8\n\nSD课程1章8内容。",
    "contentFormat": "markdown",
    "estimatedMinutes": 30,
    "difficulty": "easy",
    "knowledgePointIds": [],
    "practiceQuestionIds": [],
    "tags": [
      "SysDesign"
    ],
    "prerequisites": [],
    "updatedAt": "2026-07-03T00:00:00.000Z"
  },
  {
    "id": "sy-lesson-009",
    "courseId": "sy-course-01",
    "order": 9,
    "title": "SD课程1章9",
    "slug": "SD课程1章9",
    "summary": "SD课程1章9",
    "content": "# SD课程1章9\n\nSD课程1章9内容。",
    "contentFormat": "markdown",
    "estimatedMinutes": 30,
    "difficulty": "easy",
    "knowledgePointIds": [],
    "practiceQuestionIds": [],
    "tags": [
      "SysDesign"
    ],
    "prerequisites": [],
    "updatedAt": "2026-07-03T00:00:00.000Z"
  },
  {
    "id": "sy-lesson-010",
    "courseId": "sy-course-01",
    "order": 10,
    "title": "SD课程1章10",
    "slug": "SD课程1章10",
    "summary": "SD课程1章10",
    "content": "# SD课程1章10\n\nSD课程1章10内容。",
    "contentFormat": "markdown",
    "estimatedMinutes": 30,
    "difficulty": "easy",
    "knowledgePointIds": [],
    "practiceQuestionIds": [],
    "tags": [
      "SysDesign"
    ],
    "prerequisites": [],
    "updatedAt": "2026-07-03T00:00:00.000Z"
  },
  {
    "id": "sy-lesson-011",
    "courseId": "sy-course-01",
    "order": 11,
    "title": "SD课程1章11",
    "slug": "SD课程1章11",
    "summary": "SD课程1章11",
    "content": "# SD课程1章11\n\nSD课程1章11内容。",
    "contentFormat": "markdown",
    "estimatedMinutes": 30,
    "difficulty": "easy",
    "knowledgePointIds": [],
    "practiceQuestionIds": [],
    "tags": [
      "SysDesign"
    ],
    "prerequisites": [],
    "updatedAt": "2026-07-03T00:00:00.000Z"
  },
  {
    "id": "sy-lesson-012",
    "courseId": "sy-course-01",
    "order": 12,
    "title": "SD课程1章12",
    "slug": "SD课程1章12",
    "summary": "SD课程1章12",
    "content": "# SD课程1章12\n\nSD课程1章12内容。",
    "contentFormat": "markdown",
    "estimatedMinutes": 30,
    "difficulty": "easy",
    "knowledgePointIds": [],
    "practiceQuestionIds": [],
    "tags": [
      "SysDesign"
    ],
    "prerequisites": [],
    "updatedAt": "2026-07-03T00:00:00.000Z"
  },
  {
    "id": "sy-lesson-013",
    "courseId": "sy-course-01",
    "order": 13,
    "title": "SD课程1章13",
    "slug": "SD课程1章13",
    "summary": "SD课程1章13",
    "content": "# SD课程1章13\n\nSD课程1章13内容。",
    "contentFormat": "markdown",
    "estimatedMinutes": 30,
    "difficulty": "easy",
    "knowledgePointIds": [],
    "practiceQuestionIds": [],
    "tags": [
      "SysDesign"
    ],
    "prerequisites": [],
    "updatedAt": "2026-07-03T00:00:00.000Z"
  },
  {
    "id": "sy-lesson-014",
    "courseId": "sy-course-02",
    "order": 1,
    "title": "SD课程2章1",
    "slug": "SD课程2章1",
    "summary": "SD课程2章1",
    "content": "# SD课程2章1\n\nSD课程2章1内容。",
    "contentFormat": "markdown",
    "estimatedMinutes": 30,
    "difficulty": "easy",
    "knowledgePointIds": [],
    "practiceQuestionIds": [],
    "tags": [
      "SysDesign"
    ],
    "prerequisites": [],
    "updatedAt": "2026-07-03T00:00:00.000Z"
  },
  {
    "id": "sy-lesson-015",
    "courseId": "sy-course-02",
    "order": 2,
    "title": "SD课程2章2",
    "slug": "SD课程2章2",
    "summary": "SD课程2章2",
    "content": "# SD课程2章2\n\nSD课程2章2内容。",
    "contentFormat": "markdown",
    "estimatedMinutes": 30,
    "difficulty": "easy",
    "knowledgePointIds": [],
    "practiceQuestionIds": [],
    "tags": [
      "SysDesign"
    ],
    "prerequisites": [],
    "updatedAt": "2026-07-03T00:00:00.000Z"
  },
  {
    "id": "sy-lesson-016",
    "courseId": "sy-course-02",
    "order": 3,
    "title": "SD课程2章3",
    "slug": "SD课程2章3",
    "summary": "SD课程2章3",
    "content": "# SD课程2章3\n\nSD课程2章3内容。",
    "contentFormat": "markdown",
    "estimatedMinutes": 30,
    "difficulty": "easy",
    "knowledgePointIds": [],
    "practiceQuestionIds": [],
    "tags": [
      "SysDesign"
    ],
    "prerequisites": [],
    "updatedAt": "2026-07-03T00:00:00.000Z"
  },
  {
    "id": "sy-lesson-017",
    "courseId": "sy-course-02",
    "order": 4,
    "title": "SD课程2章4",
    "slug": "SD课程2章4",
    "summary": "SD课程2章4",
    "content": "# SD课程2章4\n\nSD课程2章4内容。",
    "contentFormat": "markdown",
    "estimatedMinutes": 30,
    "difficulty": "easy",
    "knowledgePointIds": [],
    "practiceQuestionIds": [],
    "tags": [
      "SysDesign"
    ],
    "prerequisites": [],
    "updatedAt": "2026-07-03T00:00:00.000Z"
  },
  {
    "id": "sy-lesson-018",
    "courseId": "sy-course-02",
    "order": 5,
    "title": "SD课程2章5",
    "slug": "SD课程2章5",
    "summary": "SD课程2章5",
    "content": "# SD课程2章5\n\nSD课程2章5内容。",
    "contentFormat": "markdown",
    "estimatedMinutes": 30,
    "difficulty": "easy",
    "knowledgePointIds": [],
    "practiceQuestionIds": [],
    "tags": [
      "SysDesign"
    ],
    "prerequisites": [],
    "updatedAt": "2026-07-03T00:00:00.000Z"
  },
  {
    "id": "sy-lesson-019",
    "courseId": "sy-course-02",
    "order": 6,
    "title": "SD课程2章6",
    "slug": "SD课程2章6",
    "summary": "SD课程2章6",
    "content": "# SD课程2章6\n\nSD课程2章6内容。",
    "contentFormat": "markdown",
    "estimatedMinutes": 30,
    "difficulty": "easy",
    "knowledgePointIds": [],
    "practiceQuestionIds": [],
    "tags": [
      "SysDesign"
    ],
    "prerequisites": [],
    "updatedAt": "2026-07-03T00:00:00.000Z"
  },
  {
    "id": "sy-lesson-020",
    "courseId": "sy-course-02",
    "order": 7,
    "title": "SD课程2章7",
    "slug": "SD课程2章7",
    "summary": "SD课程2章7",
    "content": "# SD课程2章7\n\nSD课程2章7内容。",
    "contentFormat": "markdown",
    "estimatedMinutes": 30,
    "difficulty": "easy",
    "knowledgePointIds": [],
    "practiceQuestionIds": [],
    "tags": [
      "SysDesign"
    ],
    "prerequisites": [],
    "updatedAt": "2026-07-03T00:00:00.000Z"
  },
  {
    "id": "sy-lesson-021",
    "courseId": "sy-course-02",
    "order": 8,
    "title": "SD课程2章8",
    "slug": "SD课程2章8",
    "summary": "SD课程2章8",
    "content": "# SD课程2章8\n\nSD课程2章8内容。",
    "contentFormat": "markdown",
    "estimatedMinutes": 30,
    "difficulty": "easy",
    "knowledgePointIds": [],
    "practiceQuestionIds": [],
    "tags": [
      "SysDesign"
    ],
    "prerequisites": [],
    "updatedAt": "2026-07-03T00:00:00.000Z"
  },
  {
    "id": "sy-lesson-022",
    "courseId": "sy-course-02",
    "order": 9,
    "title": "SD课程2章9",
    "slug": "SD课程2章9",
    "summary": "SD课程2章9",
    "content": "# SD课程2章9\n\nSD课程2章9内容。",
    "contentFormat": "markdown",
    "estimatedMinutes": 30,
    "difficulty": "easy",
    "knowledgePointIds": [],
    "practiceQuestionIds": [],
    "tags": [
      "SysDesign"
    ],
    "prerequisites": [],
    "updatedAt": "2026-07-03T00:00:00.000Z"
  },
  {
    "id": "sy-lesson-023",
    "courseId": "sy-course-02",
    "order": 10,
    "title": "SD课程2章10",
    "slug": "SD课程2章10",
    "summary": "SD课程2章10",
    "content": "# SD课程2章10\n\nSD课程2章10内容。",
    "contentFormat": "markdown",
    "estimatedMinutes": 30,
    "difficulty": "easy",
    "knowledgePointIds": [],
    "practiceQuestionIds": [],
    "tags": [
      "SysDesign"
    ],
    "prerequisites": [],
    "updatedAt": "2026-07-03T00:00:00.000Z"
  },
  {
    "id": "sy-lesson-024",
    "courseId": "sy-course-02",
    "order": 11,
    "title": "SD课程2章11",
    "slug": "SD课程2章11",
    "summary": "SD课程2章11",
    "content": "# SD课程2章11\n\nSD课程2章11内容。",
    "contentFormat": "markdown",
    "estimatedMinutes": 30,
    "difficulty": "easy",
    "knowledgePointIds": [],
    "practiceQuestionIds": [],
    "tags": [
      "SysDesign"
    ],
    "prerequisites": [],
    "updatedAt": "2026-07-03T00:00:00.000Z"
  },
  {
    "id": "sy-lesson-025",
    "courseId": "sy-course-02",
    "order": 12,
    "title": "SD课程2章12",
    "slug": "SD课程2章12",
    "summary": "SD课程2章12",
    "content": "# SD课程2章12\n\nSD课程2章12内容。",
    "contentFormat": "markdown",
    "estimatedMinutes": 30,
    "difficulty": "easy",
    "knowledgePointIds": [],
    "practiceQuestionIds": [],
    "tags": [
      "SysDesign"
    ],
    "prerequisites": [],
    "updatedAt": "2026-07-03T00:00:00.000Z"
  },
  {
    "id": "sy-lesson-026",
    "courseId": "sy-course-02",
    "order": 13,
    "title": "SD课程2章13",
    "slug": "SD课程2章13",
    "summary": "SD课程2章13",
    "content": "# SD课程2章13\n\nSD课程2章13内容。",
    "contentFormat": "markdown",
    "estimatedMinutes": 30,
    "difficulty": "easy",
    "knowledgePointIds": [],
    "practiceQuestionIds": [],
    "tags": [
      "SysDesign"
    ],
    "prerequisites": [],
    "updatedAt": "2026-07-03T00:00:00.000Z"
  },
  {
    "id": "sy-lesson-027",
    "courseId": "sy-course-03",
    "order": 1,
    "title": "SD课程3章1",
    "slug": "SD课程3章1",
    "summary": "SD课程3章1",
    "content": "# SD课程3章1\n\nSD课程3章1内容。",
    "contentFormat": "markdown",
    "estimatedMinutes": 30,
    "difficulty": "easy",
    "knowledgePointIds": [],
    "practiceQuestionIds": [],
    "tags": [
      "SysDesign"
    ],
    "prerequisites": [],
    "updatedAt": "2026-07-03T00:00:00.000Z"
  },
  {
    "id": "sy-lesson-028",
    "courseId": "sy-course-03",
    "order": 2,
    "title": "SD课程3章2",
    "slug": "SD课程3章2",
    "summary": "SD课程3章2",
    "content": "# SD课程3章2\n\nSD课程3章2内容。",
    "contentFormat": "markdown",
    "estimatedMinutes": 30,
    "difficulty": "easy",
    "knowledgePointIds": [],
    "practiceQuestionIds": [],
    "tags": [
      "SysDesign"
    ],
    "prerequisites": [],
    "updatedAt": "2026-07-03T00:00:00.000Z"
  },
  {
    "id": "sy-lesson-029",
    "courseId": "sy-course-03",
    "order": 3,
    "title": "SD课程3章3",
    "slug": "SD课程3章3",
    "summary": "SD课程3章3",
    "content": "# SD课程3章3\n\nSD课程3章3内容。",
    "contentFormat": "markdown",
    "estimatedMinutes": 30,
    "difficulty": "easy",
    "knowledgePointIds": [],
    "practiceQuestionIds": [],
    "tags": [
      "SysDesign"
    ],
    "prerequisites": [],
    "updatedAt": "2026-07-03T00:00:00.000Z"
  },
  {
    "id": "sy-lesson-030",
    "courseId": "sy-course-03",
    "order": 4,
    "title": "SD课程3章4",
    "slug": "SD课程3章4",
    "summary": "SD课程3章4",
    "content": "# SD课程3章4\n\nSD课程3章4内容。",
    "contentFormat": "markdown",
    "estimatedMinutes": 30,
    "difficulty": "easy",
    "knowledgePointIds": [],
    "practiceQuestionIds": [],
    "tags": [
      "SysDesign"
    ],
    "prerequisites": [],
    "updatedAt": "2026-07-03T00:00:00.000Z"
  },
  {
    "id": "sy-lesson-031",
    "courseId": "sy-course-03",
    "order": 5,
    "title": "SD课程3章5",
    "slug": "SD课程3章5",
    "summary": "SD课程3章5",
    "content": "# SD课程3章5\n\nSD课程3章5内容。",
    "contentFormat": "markdown",
    "estimatedMinutes": 30,
    "difficulty": "easy",
    "knowledgePointIds": [],
    "practiceQuestionIds": [],
    "tags": [
      "SysDesign"
    ],
    "prerequisites": [],
    "updatedAt": "2026-07-03T00:00:00.000Z"
  },
  {
    "id": "sy-lesson-032",
    "courseId": "sy-course-03",
    "order": 6,
    "title": "SD课程3章6",
    "slug": "SD课程3章6",
    "summary": "SD课程3章6",
    "content": "# SD课程3章6\n\nSD课程3章6内容。",
    "contentFormat": "markdown",
    "estimatedMinutes": 30,
    "difficulty": "easy",
    "knowledgePointIds": [],
    "practiceQuestionIds": [],
    "tags": [
      "SysDesign"
    ],
    "prerequisites": [],
    "updatedAt": "2026-07-03T00:00:00.000Z"
  },
  {
    "id": "sy-lesson-033",
    "courseId": "sy-course-03",
    "order": 7,
    "title": "SD课程3章7",
    "slug": "SD课程3章7",
    "summary": "SD课程3章7",
    "content": "# SD课程3章7\n\nSD课程3章7内容。",
    "contentFormat": "markdown",
    "estimatedMinutes": 30,
    "difficulty": "easy",
    "knowledgePointIds": [],
    "practiceQuestionIds": [],
    "tags": [
      "SysDesign"
    ],
    "prerequisites": [],
    "updatedAt": "2026-07-03T00:00:00.000Z"
  },
  {
    "id": "sy-lesson-034",
    "courseId": "sy-course-03",
    "order": 8,
    "title": "SD课程3章8",
    "slug": "SD课程3章8",
    "summary": "SD课程3章8",
    "content": "# SD课程3章8\n\nSD课程3章8内容。",
    "contentFormat": "markdown",
    "estimatedMinutes": 30,
    "difficulty": "easy",
    "knowledgePointIds": [],
    "practiceQuestionIds": [],
    "tags": [
      "SysDesign"
    ],
    "prerequisites": [],
    "updatedAt": "2026-07-03T00:00:00.000Z"
  },
  {
    "id": "sy-lesson-035",
    "courseId": "sy-course-03",
    "order": 9,
    "title": "SD课程3章9",
    "slug": "SD课程3章9",
    "summary": "SD课程3章9",
    "content": "# SD课程3章9\n\nSD课程3章9内容。",
    "contentFormat": "markdown",
    "estimatedMinutes": 30,
    "difficulty": "easy",
    "knowledgePointIds": [],
    "practiceQuestionIds": [],
    "tags": [
      "SysDesign"
    ],
    "prerequisites": [],
    "updatedAt": "2026-07-03T00:00:00.000Z"
  },
  {
    "id": "sy-lesson-036",
    "courseId": "sy-course-03",
    "order": 10,
    "title": "SD课程3章10",
    "slug": "SD课程3章10",
    "summary": "SD课程3章10",
    "content": "# SD课程3章10\n\nSD课程3章10内容。",
    "contentFormat": "markdown",
    "estimatedMinutes": 30,
    "difficulty": "easy",
    "knowledgePointIds": [],
    "practiceQuestionIds": [],
    "tags": [
      "SysDesign"
    ],
    "prerequisites": [],
    "updatedAt": "2026-07-03T00:00:00.000Z"
  },
  {
    "id": "sy-lesson-037",
    "courseId": "sy-course-03",
    "order": 11,
    "title": "SD课程3章11",
    "slug": "SD课程3章11",
    "summary": "SD课程3章11",
    "content": "# SD课程3章11\n\nSD课程3章11内容。",
    "contentFormat": "markdown",
    "estimatedMinutes": 30,
    "difficulty": "easy",
    "knowledgePointIds": [],
    "practiceQuestionIds": [],
    "tags": [
      "SysDesign"
    ],
    "prerequisites": [],
    "updatedAt": "2026-07-03T00:00:00.000Z"
  },
  {
    "id": "sy-lesson-038",
    "courseId": "sy-course-03",
    "order": 12,
    "title": "SD课程3章12",
    "slug": "SD课程3章12",
    "summary": "SD课程3章12",
    "content": "# SD课程3章12\n\nSD课程3章12内容。",
    "contentFormat": "markdown",
    "estimatedMinutes": 30,
    "difficulty": "easy",
    "knowledgePointIds": [],
    "practiceQuestionIds": [],
    "tags": [
      "SysDesign"
    ],
    "prerequisites": [],
    "updatedAt": "2026-07-03T00:00:00.000Z"
  },
  {
    "id": "sy-lesson-039",
    "courseId": "sy-course-03",
    "order": 13,
    "title": "SD课程3章13",
    "slug": "SD课程3章13",
    "summary": "SD课程3章13",
    "content": "# SD课程3章13\n\nSD课程3章13内容。",
    "contentFormat": "markdown",
    "estimatedMinutes": 30,
    "difficulty": "easy",
    "knowledgePointIds": [],
    "practiceQuestionIds": [],
    "tags": [
      "SysDesign"
    ],
    "prerequisites": [],
    "updatedAt": "2026-07-03T00:00:00.000Z"
  },
  {
    "id": "sy-lesson-040",
    "courseId": "sy-course-04",
    "order": 1,
    "title": "SD课程4章1",
    "slug": "SD课程4章1",
    "summary": "SD课程4章1",
    "content": "# SD课程4章1\n\nSD课程4章1内容。",
    "contentFormat": "markdown",
    "estimatedMinutes": 30,
    "difficulty": "easy",
    "knowledgePointIds": [],
    "practiceQuestionIds": [],
    "tags": [
      "SysDesign"
    ],
    "prerequisites": [],
    "updatedAt": "2026-07-03T00:00:00.000Z"
  },
  {
    "id": "sy-lesson-041",
    "courseId": "sy-course-04",
    "order": 2,
    "title": "SD课程4章2",
    "slug": "SD课程4章2",
    "summary": "SD课程4章2",
    "content": "# SD课程4章2\n\nSD课程4章2内容。",
    "contentFormat": "markdown",
    "estimatedMinutes": 30,
    "difficulty": "easy",
    "knowledgePointIds": [],
    "practiceQuestionIds": [],
    "tags": [
      "SysDesign"
    ],
    "prerequisites": [],
    "updatedAt": "2026-07-03T00:00:00.000Z"
  },
  {
    "id": "sy-lesson-042",
    "courseId": "sy-course-04",
    "order": 3,
    "title": "SD课程4章3",
    "slug": "SD课程4章3",
    "summary": "SD课程4章3",
    "content": "# SD课程4章3\n\nSD课程4章3内容。",
    "contentFormat": "markdown",
    "estimatedMinutes": 30,
    "difficulty": "easy",
    "knowledgePointIds": [],
    "practiceQuestionIds": [],
    "tags": [
      "SysDesign"
    ],
    "prerequisites": [],
    "updatedAt": "2026-07-03T00:00:00.000Z"
  },
  {
    "id": "sy-lesson-043",
    "courseId": "sy-course-04",
    "order": 4,
    "title": "SD课程4章4",
    "slug": "SD课程4章4",
    "summary": "SD课程4章4",
    "content": "# SD课程4章4\n\nSD课程4章4内容。",
    "contentFormat": "markdown",
    "estimatedMinutes": 30,
    "difficulty": "easy",
    "knowledgePointIds": [],
    "practiceQuestionIds": [],
    "tags": [
      "SysDesign"
    ],
    "prerequisites": [],
    "updatedAt": "2026-07-03T00:00:00.000Z"
  },
  {
    "id": "sy-lesson-044",
    "courseId": "sy-course-04",
    "order": 5,
    "title": "SD课程4章5",
    "slug": "SD课程4章5",
    "summary": "SD课程4章5",
    "content": "# SD课程4章5\n\nSD课程4章5内容。",
    "contentFormat": "markdown",
    "estimatedMinutes": 30,
    "difficulty": "easy",
    "knowledgePointIds": [],
    "practiceQuestionIds": [],
    "tags": [
      "SysDesign"
    ],
    "prerequisites": [],
    "updatedAt": "2026-07-03T00:00:00.000Z"
  },
  {
    "id": "sy-lesson-045",
    "courseId": "sy-course-04",
    "order": 6,
    "title": "SD课程4章6",
    "slug": "SD课程4章6",
    "summary": "SD课程4章6",
    "content": "# SD课程4章6\n\nSD课程4章6内容。",
    "contentFormat": "markdown",
    "estimatedMinutes": 30,
    "difficulty": "easy",
    "knowledgePointIds": [],
    "practiceQuestionIds": [],
    "tags": [
      "SysDesign"
    ],
    "prerequisites": [],
    "updatedAt": "2026-07-03T00:00:00.000Z"
  },
  {
    "id": "sy-lesson-046",
    "courseId": "sy-course-04",
    "order": 7,
    "title": "SD课程4章7",
    "slug": "SD课程4章7",
    "summary": "SD课程4章7",
    "content": "# SD课程4章7\n\nSD课程4章7内容。",
    "contentFormat": "markdown",
    "estimatedMinutes": 30,
    "difficulty": "easy",
    "knowledgePointIds": [],
    "practiceQuestionIds": [],
    "tags": [
      "SysDesign"
    ],
    "prerequisites": [],
    "updatedAt": "2026-07-03T00:00:00.000Z"
  },
  {
    "id": "sy-lesson-047",
    "courseId": "sy-course-04",
    "order": 8,
    "title": "SD课程4章8",
    "slug": "SD课程4章8",
    "summary": "SD课程4章8",
    "content": "# SD课程4章8\n\nSD课程4章8内容。",
    "contentFormat": "markdown",
    "estimatedMinutes": 30,
    "difficulty": "easy",
    "knowledgePointIds": [],
    "practiceQuestionIds": [],
    "tags": [
      "SysDesign"
    ],
    "prerequisites": [],
    "updatedAt": "2026-07-03T00:00:00.000Z"
  },
  {
    "id": "sy-lesson-048",
    "courseId": "sy-course-04",
    "order": 9,
    "title": "SD课程4章9",
    "slug": "SD课程4章9",
    "summary": "SD课程4章9",
    "content": "# SD课程4章9\n\nSD课程4章9内容。",
    "contentFormat": "markdown",
    "estimatedMinutes": 30,
    "difficulty": "easy",
    "knowledgePointIds": [],
    "practiceQuestionIds": [],
    "tags": [
      "SysDesign"
    ],
    "prerequisites": [],
    "updatedAt": "2026-07-03T00:00:00.000Z"
  },
  {
    "id": "sy-lesson-049",
    "courseId": "sy-course-04",
    "order": 10,
    "title": "SD课程4章10",
    "slug": "SD课程4章10",
    "summary": "SD课程4章10",
    "content": "# SD课程4章10\n\nSD课程4章10内容。",
    "contentFormat": "markdown",
    "estimatedMinutes": 30,
    "difficulty": "easy",
    "knowledgePointIds": [],
    "practiceQuestionIds": [],
    "tags": [
      "SysDesign"
    ],
    "prerequisites": [],
    "updatedAt": "2026-07-03T00:00:00.000Z"
  },
  {
    "id": "sy-lesson-050",
    "courseId": "sy-course-04",
    "order": 11,
    "title": "SD课程4章11",
    "slug": "SD课程4章11",
    "summary": "SD课程4章11",
    "content": "# SD课程4章11\n\nSD课程4章11内容。",
    "contentFormat": "markdown",
    "estimatedMinutes": 30,
    "difficulty": "easy",
    "knowledgePointIds": [],
    "practiceQuestionIds": [],
    "tags": [
      "SysDesign"
    ],
    "prerequisites": [],
    "updatedAt": "2026-07-03T00:00:00.000Z"
  },
  {
    "id": "sy-lesson-051",
    "courseId": "sy-course-04",
    "order": 12,
    "title": "SD课程4章12",
    "slug": "SD课程4章12",
    "summary": "SD课程4章12",
    "content": "# SD课程4章12\n\nSD课程4章12内容。",
    "contentFormat": "markdown",
    "estimatedMinutes": 30,
    "difficulty": "easy",
    "knowledgePointIds": [],
    "practiceQuestionIds": [],
    "tags": [
      "SysDesign"
    ],
    "prerequisites": [],
    "updatedAt": "2026-07-03T00:00:00.000Z"
  },
  {
    "id": "sy-lesson-052",
    "courseId": "sy-course-04",
    "order": 13,
    "title": "SD课程4章13",
    "slug": "SD课程4章13",
    "summary": "SD课程4章13",
    "content": "# SD课程4章13\n\nSD课程4章13内容。",
    "contentFormat": "markdown",
    "estimatedMinutes": 30,
    "difficulty": "easy",
    "knowledgePointIds": [],
    "practiceQuestionIds": [],
    "tags": [
      "SysDesign"
    ],
    "prerequisites": [],
    "updatedAt": "2026-07-03T00:00:00.000Z"
  },
  {
    "id": "sy-lesson-053",
    "courseId": "sy-course-05",
    "order": 1,
    "title": "SD课程5章1",
    "slug": "SD课程5章1",
    "summary": "SD课程5章1",
    "content": "# SD课程5章1\n\nSD课程5章1内容。",
    "contentFormat": "markdown",
    "estimatedMinutes": 30,
    "difficulty": "easy",
    "knowledgePointIds": [],
    "practiceQuestionIds": [],
    "tags": [
      "SysDesign"
    ],
    "prerequisites": [],
    "updatedAt": "2026-07-03T00:00:00.000Z"
  },
  {
    "id": "sy-lesson-054",
    "courseId": "sy-course-05",
    "order": 2,
    "title": "SD课程5章2",
    "slug": "SD课程5章2",
    "summary": "SD课程5章2",
    "content": "# SD课程5章2\n\nSD课程5章2内容。",
    "contentFormat": "markdown",
    "estimatedMinutes": 30,
    "difficulty": "easy",
    "knowledgePointIds": [],
    "practiceQuestionIds": [],
    "tags": [
      "SysDesign"
    ],
    "prerequisites": [],
    "updatedAt": "2026-07-03T00:00:00.000Z"
  },
  {
    "id": "sy-lesson-055",
    "courseId": "sy-course-05",
    "order": 3,
    "title": "SD课程5章3",
    "slug": "SD课程5章3",
    "summary": "SD课程5章3",
    "content": "# SD课程5章3\n\nSD课程5章3内容。",
    "contentFormat": "markdown",
    "estimatedMinutes": 30,
    "difficulty": "easy",
    "knowledgePointIds": [],
    "practiceQuestionIds": [],
    "tags": [
      "SysDesign"
    ],
    "prerequisites": [],
    "updatedAt": "2026-07-03T00:00:00.000Z"
  },
  {
    "id": "sy-lesson-056",
    "courseId": "sy-course-05",
    "order": 4,
    "title": "SD课程5章4",
    "slug": "SD课程5章4",
    "summary": "SD课程5章4",
    "content": "# SD课程5章4\n\nSD课程5章4内容。",
    "contentFormat": "markdown",
    "estimatedMinutes": 30,
    "difficulty": "easy",
    "knowledgePointIds": [],
    "practiceQuestionIds": [],
    "tags": [
      "SysDesign"
    ],
    "prerequisites": [],
    "updatedAt": "2026-07-03T00:00:00.000Z"
  },
  {
    "id": "sy-lesson-057",
    "courseId": "sy-course-05",
    "order": 5,
    "title": "SD课程5章5",
    "slug": "SD课程5章5",
    "summary": "SD课程5章5",
    "content": "# SD课程5章5\n\nSD课程5章5内容。",
    "contentFormat": "markdown",
    "estimatedMinutes": 30,
    "difficulty": "easy",
    "knowledgePointIds": [],
    "practiceQuestionIds": [],
    "tags": [
      "SysDesign"
    ],
    "prerequisites": [],
    "updatedAt": "2026-07-03T00:00:00.000Z"
  },
  {
    "id": "sy-lesson-058",
    "courseId": "sy-course-05",
    "order": 6,
    "title": "SD课程5章6",
    "slug": "SD课程5章6",
    "summary": "SD课程5章6",
    "content": "# SD课程5章6\n\nSD课程5章6内容。",
    "contentFormat": "markdown",
    "estimatedMinutes": 30,
    "difficulty": "easy",
    "knowledgePointIds": [],
    "practiceQuestionIds": [],
    "tags": [
      "SysDesign"
    ],
    "prerequisites": [],
    "updatedAt": "2026-07-03T00:00:00.000Z"
  },
  {
    "id": "sy-lesson-059",
    "courseId": "sy-course-05",
    "order": 7,
    "title": "SD课程5章7",
    "slug": "SD课程5章7",
    "summary": "SD课程5章7",
    "content": "# SD课程5章7\n\nSD课程5章7内容。",
    "contentFormat": "markdown",
    "estimatedMinutes": 30,
    "difficulty": "easy",
    "knowledgePointIds": [],
    "practiceQuestionIds": [],
    "tags": [
      "SysDesign"
    ],
    "prerequisites": [],
    "updatedAt": "2026-07-03T00:00:00.000Z"
  },
  {
    "id": "sy-lesson-060",
    "courseId": "sy-course-05",
    "order": 8,
    "title": "SD课程5章8",
    "slug": "SD课程5章8",
    "summary": "SD课程5章8",
    "content": "# SD课程5章8\n\nSD课程5章8内容。",
    "contentFormat": "markdown",
    "estimatedMinutes": 30,
    "difficulty": "medium",
    "knowledgePointIds": [],
    "practiceQuestionIds": [],
    "tags": [
      "SysDesign"
    ],
    "prerequisites": [],
    "updatedAt": "2026-07-03T00:00:00.000Z"
  },
  {
    "id": "sy-lesson-061",
    "courseId": "sy-course-05",
    "order": 9,
    "title": "SD课程5章9",
    "slug": "SD课程5章9",
    "summary": "SD课程5章9",
    "content": "# SD课程5章9\n\nSD课程5章9内容。",
    "contentFormat": "markdown",
    "estimatedMinutes": 30,
    "difficulty": "medium",
    "knowledgePointIds": [],
    "practiceQuestionIds": [],
    "tags": [
      "SysDesign"
    ],
    "prerequisites": [],
    "updatedAt": "2026-07-03T00:00:00.000Z"
  },
  {
    "id": "sy-lesson-062",
    "courseId": "sy-course-05",
    "order": 10,
    "title": "SD课程5章10",
    "slug": "SD课程5章10",
    "summary": "SD课程5章10",
    "content": "# SD课程5章10\n\nSD课程5章10内容。",
    "contentFormat": "markdown",
    "estimatedMinutes": 30,
    "difficulty": "medium",
    "knowledgePointIds": [],
    "practiceQuestionIds": [],
    "tags": [
      "SysDesign"
    ],
    "prerequisites": [],
    "updatedAt": "2026-07-03T00:00:00.000Z"
  },
  {
    "id": "sy-lesson-063",
    "courseId": "sy-course-05",
    "order": 11,
    "title": "SD课程5章11",
    "slug": "SD课程5章11",
    "summary": "SD课程5章11",
    "content": "# SD课程5章11\n\nSD课程5章11内容。",
    "contentFormat": "markdown",
    "estimatedMinutes": 30,
    "difficulty": "medium",
    "knowledgePointIds": [],
    "practiceQuestionIds": [],
    "tags": [
      "SysDesign"
    ],
    "prerequisites": [],
    "updatedAt": "2026-07-03T00:00:00.000Z"
  },
  {
    "id": "sy-lesson-064",
    "courseId": "sy-course-05",
    "order": 12,
    "title": "SD课程5章12",
    "slug": "SD课程5章12",
    "summary": "SD课程5章12",
    "content": "# SD课程5章12\n\nSD课程5章12内容。",
    "contentFormat": "markdown",
    "estimatedMinutes": 30,
    "difficulty": "medium",
    "knowledgePointIds": [],
    "practiceQuestionIds": [],
    "tags": [
      "SysDesign"
    ],
    "prerequisites": [],
    "updatedAt": "2026-07-03T00:00:00.000Z"
  },
  {
    "id": "sy-lesson-065",
    "courseId": "sy-course-05",
    "order": 13,
    "title": "SD课程5章13",
    "slug": "SD课程5章13",
    "summary": "SD课程5章13",
    "content": "# SD课程5章13\n\nSD课程5章13内容。",
    "contentFormat": "markdown",
    "estimatedMinutes": 30,
    "difficulty": "medium",
    "knowledgePointIds": [],
    "practiceQuestionIds": [],
    "tags": [
      "SysDesign"
    ],
    "prerequisites": [],
    "updatedAt": "2026-07-03T00:00:00.000Z"
  },
  {
    "id": "sy-lesson-066",
    "courseId": "sy-course-06",
    "order": 1,
    "title": "SD课程6章1",
    "slug": "SD课程6章1",
    "summary": "SD课程6章1",
    "content": "# SD课程6章1\n\nSD课程6章1内容。",
    "contentFormat": "markdown",
    "estimatedMinutes": 30,
    "difficulty": "medium",
    "knowledgePointIds": [],
    "practiceQuestionIds": [],
    "tags": [
      "SysDesign"
    ],
    "prerequisites": [],
    "updatedAt": "2026-07-03T00:00:00.000Z"
  },
  {
    "id": "sy-lesson-067",
    "courseId": "sy-course-06",
    "order": 2,
    "title": "SD课程6章2",
    "slug": "SD课程6章2",
    "summary": "SD课程6章2",
    "content": "# SD课程6章2\n\nSD课程6章2内容。",
    "contentFormat": "markdown",
    "estimatedMinutes": 30,
    "difficulty": "medium",
    "knowledgePointIds": [],
    "practiceQuestionIds": [],
    "tags": [
      "SysDesign"
    ],
    "prerequisites": [],
    "updatedAt": "2026-07-03T00:00:00.000Z"
  },
  {
    "id": "sy-lesson-068",
    "courseId": "sy-course-06",
    "order": 3,
    "title": "SD课程6章3",
    "slug": "SD课程6章3",
    "summary": "SD课程6章3",
    "content": "# SD课程6章3\n\nSD课程6章3内容。",
    "contentFormat": "markdown",
    "estimatedMinutes": 30,
    "difficulty": "medium",
    "knowledgePointIds": [],
    "practiceQuestionIds": [],
    "tags": [
      "SysDesign"
    ],
    "prerequisites": [],
    "updatedAt": "2026-07-03T00:00:00.000Z"
  },
  {
    "id": "sy-lesson-069",
    "courseId": "sy-course-06",
    "order": 4,
    "title": "SD课程6章4",
    "slug": "SD课程6章4",
    "summary": "SD课程6章4",
    "content": "# SD课程6章4\n\nSD课程6章4内容。",
    "contentFormat": "markdown",
    "estimatedMinutes": 30,
    "difficulty": "medium",
    "knowledgePointIds": [],
    "practiceQuestionIds": [],
    "tags": [
      "SysDesign"
    ],
    "prerequisites": [],
    "updatedAt": "2026-07-03T00:00:00.000Z"
  },
  {
    "id": "sy-lesson-070",
    "courseId": "sy-course-06",
    "order": 5,
    "title": "SD课程6章5",
    "slug": "SD课程6章5",
    "summary": "SD课程6章5",
    "content": "# SD课程6章5\n\nSD课程6章5内容。",
    "contentFormat": "markdown",
    "estimatedMinutes": 30,
    "difficulty": "medium",
    "knowledgePointIds": [],
    "practiceQuestionIds": [],
    "tags": [
      "SysDesign"
    ],
    "prerequisites": [],
    "updatedAt": "2026-07-03T00:00:00.000Z"
  },
  {
    "id": "sy-lesson-071",
    "courseId": "sy-course-06",
    "order": 6,
    "title": "SD课程6章6",
    "slug": "SD课程6章6",
    "summary": "SD课程6章6",
    "content": "# SD课程6章6\n\nSD课程6章6内容。",
    "contentFormat": "markdown",
    "estimatedMinutes": 30,
    "difficulty": "medium",
    "knowledgePointIds": [],
    "practiceQuestionIds": [],
    "tags": [
      "SysDesign"
    ],
    "prerequisites": [],
    "updatedAt": "2026-07-03T00:00:00.000Z"
  },
  {
    "id": "sy-lesson-072",
    "courseId": "sy-course-06",
    "order": 7,
    "title": "SD课程6章7",
    "slug": "SD课程6章7",
    "summary": "SD课程6章7",
    "content": "# SD课程6章7\n\nSD课程6章7内容。",
    "contentFormat": "markdown",
    "estimatedMinutes": 30,
    "difficulty": "medium",
    "knowledgePointIds": [],
    "practiceQuestionIds": [],
    "tags": [
      "SysDesign"
    ],
    "prerequisites": [],
    "updatedAt": "2026-07-03T00:00:00.000Z"
  },
  {
    "id": "sy-lesson-073",
    "courseId": "sy-course-06",
    "order": 8,
    "title": "SD课程6章8",
    "slug": "SD课程6章8",
    "summary": "SD课程6章8",
    "content": "# SD课程6章8\n\nSD课程6章8内容。",
    "contentFormat": "markdown",
    "estimatedMinutes": 30,
    "difficulty": "medium",
    "knowledgePointIds": [],
    "practiceQuestionIds": [],
    "tags": [
      "SysDesign"
    ],
    "prerequisites": [],
    "updatedAt": "2026-07-03T00:00:00.000Z"
  },
  {
    "id": "sy-lesson-074",
    "courseId": "sy-course-06",
    "order": 9,
    "title": "SD课程6章9",
    "slug": "SD课程6章9",
    "summary": "SD课程6章9",
    "content": "# SD课程6章9\n\nSD课程6章9内容。",
    "contentFormat": "markdown",
    "estimatedMinutes": 30,
    "difficulty": "medium",
    "knowledgePointIds": [],
    "practiceQuestionIds": [],
    "tags": [
      "SysDesign"
    ],
    "prerequisites": [],
    "updatedAt": "2026-07-03T00:00:00.000Z"
  },
  {
    "id": "sy-lesson-075",
    "courseId": "sy-course-06",
    "order": 10,
    "title": "SD课程6章10",
    "slug": "SD课程6章10",
    "summary": "SD课程6章10",
    "content": "# SD课程6章10\n\nSD课程6章10内容。",
    "contentFormat": "markdown",
    "estimatedMinutes": 30,
    "difficulty": "medium",
    "knowledgePointIds": [],
    "practiceQuestionIds": [],
    "tags": [
      "SysDesign"
    ],
    "prerequisites": [],
    "updatedAt": "2026-07-03T00:00:00.000Z"
  },
  {
    "id": "sy-lesson-076",
    "courseId": "sy-course-06",
    "order": 11,
    "title": "SD课程6章11",
    "slug": "SD课程6章11",
    "summary": "SD课程6章11",
    "content": "# SD课程6章11\n\nSD课程6章11内容。",
    "contentFormat": "markdown",
    "estimatedMinutes": 30,
    "difficulty": "medium",
    "knowledgePointIds": [],
    "practiceQuestionIds": [],
    "tags": [
      "SysDesign"
    ],
    "prerequisites": [],
    "updatedAt": "2026-07-03T00:00:00.000Z"
  },
  {
    "id": "sy-lesson-077",
    "courseId": "sy-course-06",
    "order": 12,
    "title": "SD课程6章12",
    "slug": "SD课程6章12",
    "summary": "SD课程6章12",
    "content": "# SD课程6章12\n\nSD课程6章12内容。",
    "contentFormat": "markdown",
    "estimatedMinutes": 30,
    "difficulty": "medium",
    "knowledgePointIds": [],
    "practiceQuestionIds": [],
    "tags": [
      "SysDesign"
    ],
    "prerequisites": [],
    "updatedAt": "2026-07-03T00:00:00.000Z"
  },
  {
    "id": "sy-lesson-078",
    "courseId": "sy-course-06",
    "order": 13,
    "title": "SD课程6章13",
    "slug": "SD课程6章13",
    "summary": "SD课程6章13",
    "content": "# SD课程6章13\n\nSD课程6章13内容。",
    "contentFormat": "markdown",
    "estimatedMinutes": 30,
    "difficulty": "medium",
    "knowledgePointIds": [],
    "practiceQuestionIds": [],
    "tags": [
      "SysDesign"
    ],
    "prerequisites": [],
    "updatedAt": "2026-07-03T00:00:00.000Z"
  },
  {
    "id": "sy-lesson-079",
    "courseId": "sy-course-07",
    "order": 1,
    "title": "SD课程7章1",
    "slug": "SD课程7章1",
    "summary": "SD课程7章1",
    "content": "# SD课程7章1\n\nSD课程7章1内容。",
    "contentFormat": "markdown",
    "estimatedMinutes": 30,
    "difficulty": "medium",
    "knowledgePointIds": [],
    "practiceQuestionIds": [],
    "tags": [
      "SysDesign"
    ],
    "prerequisites": [],
    "updatedAt": "2026-07-03T00:00:00.000Z"
  },
  {
    "id": "sy-lesson-080",
    "courseId": "sy-course-07",
    "order": 2,
    "title": "SD课程7章2",
    "slug": "SD课程7章2",
    "summary": "SD课程7章2",
    "content": "# SD课程7章2\n\nSD课程7章2内容。",
    "contentFormat": "markdown",
    "estimatedMinutes": 30,
    "difficulty": "medium",
    "knowledgePointIds": [],
    "practiceQuestionIds": [],
    "tags": [
      "SysDesign"
    ],
    "prerequisites": [],
    "updatedAt": "2026-07-03T00:00:00.000Z"
  },
  {
    "id": "sy-lesson-081",
    "courseId": "sy-course-07",
    "order": 3,
    "title": "SD课程7章3",
    "slug": "SD课程7章3",
    "summary": "SD课程7章3",
    "content": "# SD课程7章3\n\nSD课程7章3内容。",
    "contentFormat": "markdown",
    "estimatedMinutes": 30,
    "difficulty": "medium",
    "knowledgePointIds": [],
    "practiceQuestionIds": [],
    "tags": [
      "SysDesign"
    ],
    "prerequisites": [],
    "updatedAt": "2026-07-03T00:00:00.000Z"
  },
  {
    "id": "sy-lesson-082",
    "courseId": "sy-course-07",
    "order": 4,
    "title": "SD课程7章4",
    "slug": "SD课程7章4",
    "summary": "SD课程7章4",
    "content": "# SD课程7章4\n\nSD课程7章4内容。",
    "contentFormat": "markdown",
    "estimatedMinutes": 30,
    "difficulty": "medium",
    "knowledgePointIds": [],
    "practiceQuestionIds": [],
    "tags": [
      "SysDesign"
    ],
    "prerequisites": [],
    "updatedAt": "2026-07-03T00:00:00.000Z"
  },
  {
    "id": "sy-lesson-083",
    "courseId": "sy-course-07",
    "order": 5,
    "title": "SD课程7章5",
    "slug": "SD课程7章5",
    "summary": "SD课程7章5",
    "content": "# SD课程7章5\n\nSD课程7章5内容。",
    "contentFormat": "markdown",
    "estimatedMinutes": 30,
    "difficulty": "medium",
    "knowledgePointIds": [],
    "practiceQuestionIds": [],
    "tags": [
      "SysDesign"
    ],
    "prerequisites": [],
    "updatedAt": "2026-07-03T00:00:00.000Z"
  },
  {
    "id": "sy-lesson-084",
    "courseId": "sy-course-07",
    "order": 6,
    "title": "SD课程7章6",
    "slug": "SD课程7章6",
    "summary": "SD课程7章6",
    "content": "# SD课程7章6\n\nSD课程7章6内容。",
    "contentFormat": "markdown",
    "estimatedMinutes": 30,
    "difficulty": "medium",
    "knowledgePointIds": [],
    "practiceQuestionIds": [],
    "tags": [
      "SysDesign"
    ],
    "prerequisites": [],
    "updatedAt": "2026-07-03T00:00:00.000Z"
  },
  {
    "id": "sy-lesson-085",
    "courseId": "sy-course-07",
    "order": 7,
    "title": "SD课程7章7",
    "slug": "SD课程7章7",
    "summary": "SD课程7章7",
    "content": "# SD课程7章7\n\nSD课程7章7内容。",
    "contentFormat": "markdown",
    "estimatedMinutes": 30,
    "difficulty": "medium",
    "knowledgePointIds": [],
    "practiceQuestionIds": [],
    "tags": [
      "SysDesign"
    ],
    "prerequisites": [],
    "updatedAt": "2026-07-03T00:00:00.000Z"
  },
  {
    "id": "sy-lesson-086",
    "courseId": "sy-course-07",
    "order": 8,
    "title": "SD课程7章8",
    "slug": "SD课程7章8",
    "summary": "SD课程7章8",
    "content": "# SD课程7章8\n\nSD课程7章8内容。",
    "contentFormat": "markdown",
    "estimatedMinutes": 30,
    "difficulty": "medium",
    "knowledgePointIds": [],
    "practiceQuestionIds": [],
    "tags": [
      "SysDesign"
    ],
    "prerequisites": [],
    "updatedAt": "2026-07-03T00:00:00.000Z"
  },
  {
    "id": "sy-lesson-087",
    "courseId": "sy-course-07",
    "order": 9,
    "title": "SD课程7章9",
    "slug": "SD课程7章9",
    "summary": "SD课程7章9",
    "content": "# SD课程7章9\n\nSD课程7章9内容。",
    "contentFormat": "markdown",
    "estimatedMinutes": 30,
    "difficulty": "medium",
    "knowledgePointIds": [],
    "practiceQuestionIds": [],
    "tags": [
      "SysDesign"
    ],
    "prerequisites": [],
    "updatedAt": "2026-07-03T00:00:00.000Z"
  },
  {
    "id": "sy-lesson-088",
    "courseId": "sy-course-07",
    "order": 10,
    "title": "SD课程7章10",
    "slug": "SD课程7章10",
    "summary": "SD课程7章10",
    "content": "# SD课程7章10\n\nSD课程7章10内容。",
    "contentFormat": "markdown",
    "estimatedMinutes": 30,
    "difficulty": "medium",
    "knowledgePointIds": [],
    "practiceQuestionIds": [],
    "tags": [
      "SysDesign"
    ],
    "prerequisites": [],
    "updatedAt": "2026-07-03T00:00:00.000Z"
  },
  {
    "id": "sy-lesson-089",
    "courseId": "sy-course-07",
    "order": 11,
    "title": "SD课程7章11",
    "slug": "SD课程7章11",
    "summary": "SD课程7章11",
    "content": "# SD课程7章11\n\nSD课程7章11内容。",
    "contentFormat": "markdown",
    "estimatedMinutes": 30,
    "difficulty": "medium",
    "knowledgePointIds": [],
    "practiceQuestionIds": [],
    "tags": [
      "SysDesign"
    ],
    "prerequisites": [],
    "updatedAt": "2026-07-03T00:00:00.000Z"
  },
  {
    "id": "sy-lesson-090",
    "courseId": "sy-course-07",
    "order": 12,
    "title": "SD课程7章12",
    "slug": "SD课程7章12",
    "summary": "SD课程7章12",
    "content": "# SD课程7章12\n\nSD课程7章12内容。",
    "contentFormat": "markdown",
    "estimatedMinutes": 30,
    "difficulty": "medium",
    "knowledgePointIds": [],
    "practiceQuestionIds": [],
    "tags": [
      "SysDesign"
    ],
    "prerequisites": [],
    "updatedAt": "2026-07-03T00:00:00.000Z"
  },
  {
    "id": "sy-lesson-091",
    "courseId": "sy-course-07",
    "order": 13,
    "title": "SD课程7章13",
    "slug": "SD课程7章13",
    "summary": "SD课程7章13",
    "content": "# SD课程7章13\n\nSD课程7章13内容。",
    "contentFormat": "markdown",
    "estimatedMinutes": 30,
    "difficulty": "medium",
    "knowledgePointIds": [],
    "practiceQuestionIds": [],
    "tags": [
      "SysDesign"
    ],
    "prerequisites": [],
    "updatedAt": "2026-07-03T00:00:00.000Z"
  },
  {
    "id": "sy-lesson-092",
    "courseId": "sy-course-08",
    "order": 1,
    "title": "SD课程8章1",
    "slug": "SD课程8章1",
    "summary": "SD课程8章1",
    "content": "# SD课程8章1\n\nSD课程8章1内容。",
    "contentFormat": "markdown",
    "estimatedMinutes": 30,
    "difficulty": "medium",
    "knowledgePointIds": [],
    "practiceQuestionIds": [],
    "tags": [
      "SysDesign"
    ],
    "prerequisites": [],
    "updatedAt": "2026-07-03T00:00:00.000Z"
  },
  {
    "id": "sy-lesson-093",
    "courseId": "sy-course-08",
    "order": 2,
    "title": "SD课程8章2",
    "slug": "SD课程8章2",
    "summary": "SD课程8章2",
    "content": "# SD课程8章2\n\nSD课程8章2内容。",
    "contentFormat": "markdown",
    "estimatedMinutes": 30,
    "difficulty": "medium",
    "knowledgePointIds": [],
    "practiceQuestionIds": [],
    "tags": [
      "SysDesign"
    ],
    "prerequisites": [],
    "updatedAt": "2026-07-03T00:00:00.000Z"
  },
  {
    "id": "sy-lesson-094",
    "courseId": "sy-course-08",
    "order": 3,
    "title": "SD课程8章3",
    "slug": "SD课程8章3",
    "summary": "SD课程8章3",
    "content": "# SD课程8章3\n\nSD课程8章3内容。",
    "contentFormat": "markdown",
    "estimatedMinutes": 30,
    "difficulty": "medium",
    "knowledgePointIds": [],
    "practiceQuestionIds": [],
    "tags": [
      "SysDesign"
    ],
    "prerequisites": [],
    "updatedAt": "2026-07-03T00:00:00.000Z"
  },
  {
    "id": "sy-lesson-095",
    "courseId": "sy-course-08",
    "order": 4,
    "title": "SD课程8章4",
    "slug": "SD课程8章4",
    "summary": "SD课程8章4",
    "content": "# SD课程8章4\n\nSD课程8章4内容。",
    "contentFormat": "markdown",
    "estimatedMinutes": 30,
    "difficulty": "medium",
    "knowledgePointIds": [],
    "practiceQuestionIds": [],
    "tags": [
      "SysDesign"
    ],
    "prerequisites": [],
    "updatedAt": "2026-07-03T00:00:00.000Z"
  },
  {
    "id": "sy-lesson-096",
    "courseId": "sy-course-08",
    "order": 5,
    "title": "SD课程8章5",
    "slug": "SD课程8章5",
    "summary": "SD课程8章5",
    "content": "# SD课程8章5\n\nSD课程8章5内容。",
    "contentFormat": "markdown",
    "estimatedMinutes": 30,
    "difficulty": "medium",
    "knowledgePointIds": [],
    "practiceQuestionIds": [],
    "tags": [
      "SysDesign"
    ],
    "prerequisites": [],
    "updatedAt": "2026-07-03T00:00:00.000Z"
  },
  {
    "id": "sy-lesson-097",
    "courseId": "sy-course-08",
    "order": 6,
    "title": "SD课程8章6",
    "slug": "SD课程8章6",
    "summary": "SD课程8章6",
    "content": "# SD课程8章6\n\nSD课程8章6内容。",
    "contentFormat": "markdown",
    "estimatedMinutes": 30,
    "difficulty": "medium",
    "knowledgePointIds": [],
    "practiceQuestionIds": [],
    "tags": [
      "SysDesign"
    ],
    "prerequisites": [],
    "updatedAt": "2026-07-03T00:00:00.000Z"
  },
  {
    "id": "sy-lesson-098",
    "courseId": "sy-course-08",
    "order": 7,
    "title": "SD课程8章7",
    "slug": "SD课程8章7",
    "summary": "SD课程8章7",
    "content": "# SD课程8章7\n\nSD课程8章7内容。",
    "contentFormat": "markdown",
    "estimatedMinutes": 30,
    "difficulty": "medium",
    "knowledgePointIds": [],
    "practiceQuestionIds": [],
    "tags": [
      "SysDesign"
    ],
    "prerequisites": [],
    "updatedAt": "2026-07-03T00:00:00.000Z"
  },
  {
    "id": "sy-lesson-099",
    "courseId": "sy-course-08",
    "order": 8,
    "title": "SD课程8章8",
    "slug": "SD课程8章8",
    "summary": "SD课程8章8",
    "content": "# SD课程8章8\n\nSD课程8章8内容。",
    "contentFormat": "markdown",
    "estimatedMinutes": 30,
    "difficulty": "medium",
    "knowledgePointIds": [],
    "practiceQuestionIds": [],
    "tags": [
      "SysDesign"
    ],
    "prerequisites": [],
    "updatedAt": "2026-07-03T00:00:00.000Z"
  },
  {
    "id": "sy-lesson-100",
    "courseId": "sy-course-08",
    "order": 9,
    "title": "SD课程8章9",
    "slug": "SD课程8章9",
    "summary": "SD课程8章9",
    "content": "# SD课程8章9\n\nSD课程8章9内容。",
    "contentFormat": "markdown",
    "estimatedMinutes": 30,
    "difficulty": "medium",
    "knowledgePointIds": [],
    "practiceQuestionIds": [],
    "tags": [
      "SysDesign"
    ],
    "prerequisites": [],
    "updatedAt": "2026-07-03T00:00:00.000Z"
  },
  {
    "id": "sy-lesson-101",
    "courseId": "sy-course-08",
    "order": 10,
    "title": "SD课程8章10",
    "slug": "SD课程8章10",
    "summary": "SD课程8章10",
    "content": "# SD课程8章10\n\nSD课程8章10内容。",
    "contentFormat": "markdown",
    "estimatedMinutes": 30,
    "difficulty": "medium",
    "knowledgePointIds": [],
    "practiceQuestionIds": [],
    "tags": [
      "SysDesign"
    ],
    "prerequisites": [],
    "updatedAt": "2026-07-03T00:00:00.000Z"
  },
  {
    "id": "sy-lesson-102",
    "courseId": "sy-course-08",
    "order": 11,
    "title": "SD课程8章11",
    "slug": "SD课程8章11",
    "summary": "SD课程8章11",
    "content": "# SD课程8章11\n\nSD课程8章11内容。",
    "contentFormat": "markdown",
    "estimatedMinutes": 30,
    "difficulty": "medium",
    "knowledgePointIds": [],
    "practiceQuestionIds": [],
    "tags": [
      "SysDesign"
    ],
    "prerequisites": [],
    "updatedAt": "2026-07-03T00:00:00.000Z"
  },
  {
    "id": "sy-lesson-103",
    "courseId": "sy-course-08",
    "order": 12,
    "title": "SD课程8章12",
    "slug": "SD课程8章12",
    "summary": "SD课程8章12",
    "content": "# SD课程8章12\n\nSD课程8章12内容。",
    "contentFormat": "markdown",
    "estimatedMinutes": 30,
    "difficulty": "medium",
    "knowledgePointIds": [],
    "practiceQuestionIds": [],
    "tags": [
      "SysDesign"
    ],
    "prerequisites": [],
    "updatedAt": "2026-07-03T00:00:00.000Z"
  },
  {
    "id": "sy-lesson-104",
    "courseId": "sy-course-08",
    "order": 13,
    "title": "SD课程8章13",
    "slug": "SD课程8章13",
    "summary": "SD课程8章13",
    "content": "# SD课程8章13\n\nSD课程8章13内容。",
    "contentFormat": "markdown",
    "estimatedMinutes": 30,
    "difficulty": "medium",
    "knowledgePointIds": [],
    "practiceQuestionIds": [],
    "tags": [
      "SysDesign"
    ],
    "prerequisites": [],
    "updatedAt": "2026-07-03T00:00:00.000Z"
  },
  {
    "id": "sy-lesson-105",
    "courseId": "sy-course-09",
    "order": 1,
    "title": "SD课程9章1",
    "slug": "SD课程9章1",
    "summary": "SD课程9章1",
    "content": "# SD课程9章1\n\nSD课程9章1内容。",
    "contentFormat": "markdown",
    "estimatedMinutes": 30,
    "difficulty": "medium",
    "knowledgePointIds": [],
    "practiceQuestionIds": [],
    "tags": [
      "SysDesign"
    ],
    "prerequisites": [],
    "updatedAt": "2026-07-03T00:00:00.000Z"
  },
  {
    "id": "sy-lesson-106",
    "courseId": "sy-course-09",
    "order": 2,
    "title": "SD课程9章2",
    "slug": "SD课程9章2",
    "summary": "SD课程9章2",
    "content": "# SD课程9章2\n\nSD课程9章2内容。",
    "contentFormat": "markdown",
    "estimatedMinutes": 30,
    "difficulty": "medium",
    "knowledgePointIds": [],
    "practiceQuestionIds": [],
    "tags": [
      "SysDesign"
    ],
    "prerequisites": [],
    "updatedAt": "2026-07-03T00:00:00.000Z"
  },
  {
    "id": "sy-lesson-107",
    "courseId": "sy-course-09",
    "order": 3,
    "title": "SD课程9章3",
    "slug": "SD课程9章3",
    "summary": "SD课程9章3",
    "content": "# SD课程9章3\n\nSD课程9章3内容。",
    "contentFormat": "markdown",
    "estimatedMinutes": 30,
    "difficulty": "medium",
    "knowledgePointIds": [],
    "practiceQuestionIds": [],
    "tags": [
      "SysDesign"
    ],
    "prerequisites": [],
    "updatedAt": "2026-07-03T00:00:00.000Z"
  },
  {
    "id": "sy-lesson-108",
    "courseId": "sy-course-09",
    "order": 4,
    "title": "SD课程9章4",
    "slug": "SD课程9章4",
    "summary": "SD课程9章4",
    "content": "# SD课程9章4\n\nSD课程9章4内容。",
    "contentFormat": "markdown",
    "estimatedMinutes": 30,
    "difficulty": "medium",
    "knowledgePointIds": [],
    "practiceQuestionIds": [],
    "tags": [
      "SysDesign"
    ],
    "prerequisites": [],
    "updatedAt": "2026-07-03T00:00:00.000Z"
  },
  {
    "id": "sy-lesson-109",
    "courseId": "sy-course-09",
    "order": 5,
    "title": "SD课程9章5",
    "slug": "SD课程9章5",
    "summary": "SD课程9章5",
    "content": "# SD课程9章5\n\nSD课程9章5内容。",
    "contentFormat": "markdown",
    "estimatedMinutes": 30,
    "difficulty": "medium",
    "knowledgePointIds": [],
    "practiceQuestionIds": [],
    "tags": [
      "SysDesign"
    ],
    "prerequisites": [],
    "updatedAt": "2026-07-03T00:00:00.000Z"
  },
  {
    "id": "sy-lesson-110",
    "courseId": "sy-course-09",
    "order": 6,
    "title": "SD课程9章6",
    "slug": "SD课程9章6",
    "summary": "SD课程9章6",
    "content": "# SD课程9章6\n\nSD课程9章6内容。",
    "contentFormat": "markdown",
    "estimatedMinutes": 30,
    "difficulty": "medium",
    "knowledgePointIds": [],
    "practiceQuestionIds": [],
    "tags": [
      "SysDesign"
    ],
    "prerequisites": [],
    "updatedAt": "2026-07-03T00:00:00.000Z"
  },
  {
    "id": "sy-lesson-111",
    "courseId": "sy-course-09",
    "order": 7,
    "title": "SD课程9章7",
    "slug": "SD课程9章7",
    "summary": "SD课程9章7",
    "content": "# SD课程9章7\n\nSD课程9章7内容。",
    "contentFormat": "markdown",
    "estimatedMinutes": 30,
    "difficulty": "medium",
    "knowledgePointIds": [],
    "practiceQuestionIds": [],
    "tags": [
      "SysDesign"
    ],
    "prerequisites": [],
    "updatedAt": "2026-07-03T00:00:00.000Z"
  },
  {
    "id": "sy-lesson-112",
    "courseId": "sy-course-09",
    "order": 8,
    "title": "SD课程9章8",
    "slug": "SD课程9章8",
    "summary": "SD课程9章8",
    "content": "# SD课程9章8\n\nSD课程9章8内容。",
    "contentFormat": "markdown",
    "estimatedMinutes": 30,
    "difficulty": "medium",
    "knowledgePointIds": [],
    "practiceQuestionIds": [],
    "tags": [
      "SysDesign"
    ],
    "prerequisites": [],
    "updatedAt": "2026-07-03T00:00:00.000Z"
  },
  {
    "id": "sy-lesson-113",
    "courseId": "sy-course-09",
    "order": 9,
    "title": "SD课程9章9",
    "slug": "SD课程9章9",
    "summary": "SD课程9章9",
    "content": "# SD课程9章9\n\nSD课程9章9内容。",
    "contentFormat": "markdown",
    "estimatedMinutes": 30,
    "difficulty": "medium",
    "knowledgePointIds": [],
    "practiceQuestionIds": [],
    "tags": [
      "SysDesign"
    ],
    "prerequisites": [],
    "updatedAt": "2026-07-03T00:00:00.000Z"
  },
  {
    "id": "sy-lesson-114",
    "courseId": "sy-course-09",
    "order": 10,
    "title": "SD课程9章10",
    "slug": "SD课程9章10",
    "summary": "SD课程9章10",
    "content": "# SD课程9章10\n\nSD课程9章10内容。",
    "contentFormat": "markdown",
    "estimatedMinutes": 30,
    "difficulty": "medium",
    "knowledgePointIds": [],
    "practiceQuestionIds": [],
    "tags": [
      "SysDesign"
    ],
    "prerequisites": [],
    "updatedAt": "2026-07-03T00:00:00.000Z"
  },
  {
    "id": "sy-lesson-115",
    "courseId": "sy-course-09",
    "order": 11,
    "title": "SD课程9章11",
    "slug": "SD课程9章11",
    "summary": "SD课程9章11",
    "content": "# SD课程9章11\n\nSD课程9章11内容。",
    "contentFormat": "markdown",
    "estimatedMinutes": 30,
    "difficulty": "medium",
    "knowledgePointIds": [],
    "practiceQuestionIds": [],
    "tags": [
      "SysDesign"
    ],
    "prerequisites": [],
    "updatedAt": "2026-07-03T00:00:00.000Z"
  },
  {
    "id": "sy-lesson-116",
    "courseId": "sy-course-09",
    "order": 12,
    "title": "SD课程9章12",
    "slug": "SD课程9章12",
    "summary": "SD课程9章12",
    "content": "# SD课程9章12\n\nSD课程9章12内容。",
    "contentFormat": "markdown",
    "estimatedMinutes": 30,
    "difficulty": "medium",
    "knowledgePointIds": [],
    "practiceQuestionIds": [],
    "tags": [
      "SysDesign"
    ],
    "prerequisites": [],
    "updatedAt": "2026-07-03T00:00:00.000Z"
  },
  {
    "id": "sy-lesson-117",
    "courseId": "sy-course-09",
    "order": 13,
    "title": "SD课程9章13",
    "slug": "SD课程9章13",
    "summary": "SD课程9章13",
    "content": "# SD课程9章13\n\nSD课程9章13内容。",
    "contentFormat": "markdown",
    "estimatedMinutes": 30,
    "difficulty": "medium",
    "knowledgePointIds": [],
    "practiceQuestionIds": [],
    "tags": [
      "SysDesign"
    ],
    "prerequisites": [],
    "updatedAt": "2026-07-03T00:00:00.000Z"
  },
  {
    "id": "sy-lesson-118",
    "courseId": "sy-course-10",
    "order": 1,
    "title": "SD课程10章1",
    "slug": "SD课程10章1",
    "summary": "SD课程10章1",
    "content": "# SD课程10章1\n\nSD课程10章1内容。",
    "contentFormat": "markdown",
    "estimatedMinutes": 30,
    "difficulty": "medium",
    "knowledgePointIds": [],
    "practiceQuestionIds": [],
    "tags": [
      "SysDesign"
    ],
    "prerequisites": [],
    "updatedAt": "2026-07-03T00:00:00.000Z"
  },
  {
    "id": "sy-lesson-119",
    "courseId": "sy-course-10",
    "order": 2,
    "title": "SD课程10章2",
    "slug": "SD课程10章2",
    "summary": "SD课程10章2",
    "content": "# SD课程10章2\n\nSD课程10章2内容。",
    "contentFormat": "markdown",
    "estimatedMinutes": 30,
    "difficulty": "medium",
    "knowledgePointIds": [],
    "practiceQuestionIds": [],
    "tags": [
      "SysDesign"
    ],
    "prerequisites": [],
    "updatedAt": "2026-07-03T00:00:00.000Z"
  },
  {
    "id": "sy-lesson-120",
    "courseId": "sy-course-10",
    "order": 3,
    "title": "SD课程10章3",
    "slug": "SD课程10章3",
    "summary": "SD课程10章3",
    "content": "# SD课程10章3\n\nSD课程10章3内容。",
    "contentFormat": "markdown",
    "estimatedMinutes": 30,
    "difficulty": "medium",
    "knowledgePointIds": [],
    "practiceQuestionIds": [],
    "tags": [
      "SysDesign"
    ],
    "prerequisites": [],
    "updatedAt": "2026-07-03T00:00:00.000Z"
  },
  {
    "id": "sy-lesson-121",
    "courseId": "sy-course-10",
    "order": 4,
    "title": "SD课程10章4",
    "slug": "SD课程10章4",
    "summary": "SD课程10章4",
    "content": "# SD课程10章4\n\nSD课程10章4内容。",
    "contentFormat": "markdown",
    "estimatedMinutes": 30,
    "difficulty": "medium",
    "knowledgePointIds": [],
    "practiceQuestionIds": [],
    "tags": [
      "SysDesign"
    ],
    "prerequisites": [],
    "updatedAt": "2026-07-03T00:00:00.000Z"
  },
  {
    "id": "sy-lesson-122",
    "courseId": "sy-course-10",
    "order": 5,
    "title": "SD课程10章5",
    "slug": "SD课程10章5",
    "summary": "SD课程10章5",
    "content": "# SD课程10章5\n\nSD课程10章5内容。",
    "contentFormat": "markdown",
    "estimatedMinutes": 30,
    "difficulty": "medium",
    "knowledgePointIds": [],
    "practiceQuestionIds": [],
    "tags": [
      "SysDesign"
    ],
    "prerequisites": [],
    "updatedAt": "2026-07-03T00:00:00.000Z"
  },
  {
    "id": "sy-lesson-123",
    "courseId": "sy-course-10",
    "order": 6,
    "title": "SD课程10章6",
    "slug": "SD课程10章6",
    "summary": "SD课程10章6",
    "content": "# SD课程10章6\n\nSD课程10章6内容。",
    "contentFormat": "markdown",
    "estimatedMinutes": 30,
    "difficulty": "medium",
    "knowledgePointIds": [],
    "practiceQuestionIds": [],
    "tags": [
      "SysDesign"
    ],
    "prerequisites": [],
    "updatedAt": "2026-07-03T00:00:00.000Z"
  },
  {
    "id": "sy-lesson-124",
    "courseId": "sy-course-10",
    "order": 7,
    "title": "SD课程10章7",
    "slug": "SD课程10章7",
    "summary": "SD课程10章7",
    "content": "# SD课程10章7\n\nSD课程10章7内容。",
    "contentFormat": "markdown",
    "estimatedMinutes": 30,
    "difficulty": "medium",
    "knowledgePointIds": [],
    "practiceQuestionIds": [],
    "tags": [
      "SysDesign"
    ],
    "prerequisites": [],
    "updatedAt": "2026-07-03T00:00:00.000Z"
  },
  {
    "id": "sy-lesson-125",
    "courseId": "sy-course-10",
    "order": 8,
    "title": "SD课程10章8",
    "slug": "SD课程10章8",
    "summary": "SD课程10章8",
    "content": "# SD课程10章8\n\nSD课程10章8内容。",
    "contentFormat": "markdown",
    "estimatedMinutes": 30,
    "difficulty": "medium",
    "knowledgePointIds": [],
    "practiceQuestionIds": [],
    "tags": [
      "SysDesign"
    ],
    "prerequisites": [],
    "updatedAt": "2026-07-03T00:00:00.000Z"
  },
  {
    "id": "sy-lesson-126",
    "courseId": "sy-course-10",
    "order": 9,
    "title": "SD课程10章9",
    "slug": "SD课程10章9",
    "summary": "SD课程10章9",
    "content": "# SD课程10章9\n\nSD课程10章9内容。",
    "contentFormat": "markdown",
    "estimatedMinutes": 30,
    "difficulty": "medium",
    "knowledgePointIds": [],
    "practiceQuestionIds": [],
    "tags": [
      "SysDesign"
    ],
    "prerequisites": [],
    "updatedAt": "2026-07-03T00:00:00.000Z"
  },
  {
    "id": "sy-lesson-127",
    "courseId": "sy-course-10",
    "order": 10,
    "title": "SD课程10章10",
    "slug": "SD课程10章10",
    "summary": "SD课程10章10",
    "content": "# SD课程10章10\n\nSD课程10章10内容。",
    "contentFormat": "markdown",
    "estimatedMinutes": 30,
    "difficulty": "medium",
    "knowledgePointIds": [],
    "practiceQuestionIds": [],
    "tags": [
      "SysDesign"
    ],
    "prerequisites": [],
    "updatedAt": "2026-07-03T00:00:00.000Z"
  },
  {
    "id": "sy-lesson-128",
    "courseId": "sy-course-10",
    "order": 11,
    "title": "SD课程10章11",
    "slug": "SD课程10章11",
    "summary": "SD课程10章11",
    "content": "# SD课程10章11\n\nSD课程10章11内容。",
    "contentFormat": "markdown",
    "estimatedMinutes": 30,
    "difficulty": "medium",
    "knowledgePointIds": [],
    "practiceQuestionIds": [],
    "tags": [
      "SysDesign"
    ],
    "prerequisites": [],
    "updatedAt": "2026-07-03T00:00:00.000Z"
  },
  {
    "id": "sy-lesson-129",
    "courseId": "sy-course-10",
    "order": 12,
    "title": "SD课程10章12",
    "slug": "SD课程10章12",
    "summary": "SD课程10章12",
    "content": "# SD课程10章12\n\nSD课程10章12内容。",
    "contentFormat": "markdown",
    "estimatedMinutes": 30,
    "difficulty": "medium",
    "knowledgePointIds": [],
    "practiceQuestionIds": [],
    "tags": [
      "SysDesign"
    ],
    "prerequisites": [],
    "updatedAt": "2026-07-03T00:00:00.000Z"
  },
  {
    "id": "sy-lesson-130",
    "courseId": "sy-course-10",
    "order": 13,
    "title": "SD课程10章13",
    "slug": "SD课程10章13",
    "summary": "SD课程10章13",
    "content": "# SD课程10章13\n\nSD课程10章13内容。",
    "contentFormat": "markdown",
    "estimatedMinutes": 30,
    "difficulty": "hard",
    "knowledgePointIds": [],
    "practiceQuestionIds": [],
    "tags": [
      "SysDesign"
    ],
    "prerequisites": [],
    "updatedAt": "2026-07-03T00:00:00.000Z"
  },
  {
    "id": "sy-lesson-131",
    "courseId": "sy-course-11",
    "order": 1,
    "title": "SD课程11章1",
    "slug": "SD课程11章1",
    "summary": "SD课程11章1",
    "content": "# SD课程11章1\n\nSD课程11章1内容。",
    "contentFormat": "markdown",
    "estimatedMinutes": 30,
    "difficulty": "hard",
    "knowledgePointIds": [],
    "practiceQuestionIds": [],
    "tags": [
      "SysDesign"
    ],
    "prerequisites": [],
    "updatedAt": "2026-07-03T00:00:00.000Z"
  },
  {
    "id": "sy-lesson-132",
    "courseId": "sy-course-11",
    "order": 2,
    "title": "SD课程11章2",
    "slug": "SD课程11章2",
    "summary": "SD课程11章2",
    "content": "# SD课程11章2\n\nSD课程11章2内容。",
    "contentFormat": "markdown",
    "estimatedMinutes": 30,
    "difficulty": "hard",
    "knowledgePointIds": [],
    "practiceQuestionIds": [],
    "tags": [
      "SysDesign"
    ],
    "prerequisites": [],
    "updatedAt": "2026-07-03T00:00:00.000Z"
  },
  {
    "id": "sy-lesson-133",
    "courseId": "sy-course-11",
    "order": 3,
    "title": "SD课程11章3",
    "slug": "SD课程11章3",
    "summary": "SD课程11章3",
    "content": "# SD课程11章3\n\nSD课程11章3内容。",
    "contentFormat": "markdown",
    "estimatedMinutes": 30,
    "difficulty": "hard",
    "knowledgePointIds": [],
    "practiceQuestionIds": [],
    "tags": [
      "SysDesign"
    ],
    "prerequisites": [],
    "updatedAt": "2026-07-03T00:00:00.000Z"
  },
  {
    "id": "sy-lesson-134",
    "courseId": "sy-course-11",
    "order": 4,
    "title": "SD课程11章4",
    "slug": "SD课程11章4",
    "summary": "SD课程11章4",
    "content": "# SD课程11章4\n\nSD课程11章4内容。",
    "contentFormat": "markdown",
    "estimatedMinutes": 30,
    "difficulty": "hard",
    "knowledgePointIds": [],
    "practiceQuestionIds": [],
    "tags": [
      "SysDesign"
    ],
    "prerequisites": [],
    "updatedAt": "2026-07-03T00:00:00.000Z"
  },
  {
    "id": "sy-lesson-135",
    "courseId": "sy-course-11",
    "order": 5,
    "title": "SD课程11章5",
    "slug": "SD课程11章5",
    "summary": "SD课程11章5",
    "content": "# SD课程11章5\n\nSD课程11章5内容。",
    "contentFormat": "markdown",
    "estimatedMinutes": 30,
    "difficulty": "hard",
    "knowledgePointIds": [],
    "practiceQuestionIds": [],
    "tags": [
      "SysDesign"
    ],
    "prerequisites": [],
    "updatedAt": "2026-07-03T00:00:00.000Z"
  },
  {
    "id": "sy-lesson-136",
    "courseId": "sy-course-11",
    "order": 6,
    "title": "SD课程11章6",
    "slug": "SD课程11章6",
    "summary": "SD课程11章6",
    "content": "# SD课程11章6\n\nSD课程11章6内容。",
    "contentFormat": "markdown",
    "estimatedMinutes": 30,
    "difficulty": "hard",
    "knowledgePointIds": [],
    "practiceQuestionIds": [],
    "tags": [
      "SysDesign"
    ],
    "prerequisites": [],
    "updatedAt": "2026-07-03T00:00:00.000Z"
  },
  {
    "id": "sy-lesson-137",
    "courseId": "sy-course-11",
    "order": 7,
    "title": "SD课程11章7",
    "slug": "SD课程11章7",
    "summary": "SD课程11章7",
    "content": "# SD课程11章7\n\nSD课程11章7内容。",
    "contentFormat": "markdown",
    "estimatedMinutes": 30,
    "difficulty": "hard",
    "knowledgePointIds": [],
    "practiceQuestionIds": [],
    "tags": [
      "SysDesign"
    ],
    "prerequisites": [],
    "updatedAt": "2026-07-03T00:00:00.000Z"
  },
  {
    "id": "sy-lesson-138",
    "courseId": "sy-course-11",
    "order": 8,
    "title": "SD课程11章8",
    "slug": "SD课程11章8",
    "summary": "SD课程11章8",
    "content": "# SD课程11章8\n\nSD课程11章8内容。",
    "contentFormat": "markdown",
    "estimatedMinutes": 30,
    "difficulty": "hard",
    "knowledgePointIds": [],
    "practiceQuestionIds": [],
    "tags": [
      "SysDesign"
    ],
    "prerequisites": [],
    "updatedAt": "2026-07-03T00:00:00.000Z"
  },
  {
    "id": "sy-lesson-139",
    "courseId": "sy-course-11",
    "order": 9,
    "title": "SD课程11章9",
    "slug": "SD课程11章9",
    "summary": "SD课程11章9",
    "content": "# SD课程11章9\n\nSD课程11章9内容。",
    "contentFormat": "markdown",
    "estimatedMinutes": 30,
    "difficulty": "hard",
    "knowledgePointIds": [],
    "practiceQuestionIds": [],
    "tags": [
      "SysDesign"
    ],
    "prerequisites": [],
    "updatedAt": "2026-07-03T00:00:00.000Z"
  },
  {
    "id": "sy-lesson-140",
    "courseId": "sy-course-11",
    "order": 10,
    "title": "SD课程11章10",
    "slug": "SD课程11章10",
    "summary": "SD课程11章10",
    "content": "# SD课程11章10\n\nSD课程11章10内容。",
    "contentFormat": "markdown",
    "estimatedMinutes": 30,
    "difficulty": "hard",
    "knowledgePointIds": [],
    "practiceQuestionIds": [],
    "tags": [
      "SysDesign"
    ],
    "prerequisites": [],
    "updatedAt": "2026-07-03T00:00:00.000Z"
  },
  {
    "id": "sy-lesson-141",
    "courseId": "sy-course-11",
    "order": 11,
    "title": "SD课程11章11",
    "slug": "SD课程11章11",
    "summary": "SD课程11章11",
    "content": "# SD课程11章11\n\nSD课程11章11内容。",
    "contentFormat": "markdown",
    "estimatedMinutes": 30,
    "difficulty": "hard",
    "knowledgePointIds": [],
    "practiceQuestionIds": [],
    "tags": [
      "SysDesign"
    ],
    "prerequisites": [],
    "updatedAt": "2026-07-03T00:00:00.000Z"
  },
  {
    "id": "sy-lesson-142",
    "courseId": "sy-course-11",
    "order": 12,
    "title": "SD课程11章12",
    "slug": "SD课程11章12",
    "summary": "SD课程11章12",
    "content": "# SD课程11章12\n\nSD课程11章12内容。",
    "contentFormat": "markdown",
    "estimatedMinutes": 30,
    "difficulty": "hard",
    "knowledgePointIds": [],
    "practiceQuestionIds": [],
    "tags": [
      "SysDesign"
    ],
    "prerequisites": [],
    "updatedAt": "2026-07-03T00:00:00.000Z"
  },
  {
    "id": "sy-lesson-143",
    "courseId": "sy-course-11",
    "order": 13,
    "title": "SD课程11章13",
    "slug": "SD课程11章13",
    "summary": "SD课程11章13",
    "content": "# SD课程11章13\n\nSD课程11章13内容。",
    "contentFormat": "markdown",
    "estimatedMinutes": 30,
    "difficulty": "hard",
    "knowledgePointIds": [],
    "practiceQuestionIds": [],
    "tags": [
      "SysDesign"
    ],
    "prerequisites": [],
    "updatedAt": "2026-07-03T00:00:00.000Z"
  },
  {
    "id": "sy-lesson-144",
    "courseId": "sy-course-12",
    "order": 1,
    "title": "SD课程12章1",
    "slug": "SD课程12章1",
    "summary": "SD课程12章1",
    "content": "# SD课程12章1\n\nSD课程12章1内容。",
    "contentFormat": "markdown",
    "estimatedMinutes": 30,
    "difficulty": "hard",
    "knowledgePointIds": [],
    "practiceQuestionIds": [],
    "tags": [
      "SysDesign"
    ],
    "prerequisites": [],
    "updatedAt": "2026-07-03T00:00:00.000Z"
  },
  {
    "id": "sy-lesson-145",
    "courseId": "sy-course-12",
    "order": 2,
    "title": "SD课程12章2",
    "slug": "SD课程12章2",
    "summary": "SD课程12章2",
    "content": "# SD课程12章2\n\nSD课程12章2内容。",
    "contentFormat": "markdown",
    "estimatedMinutes": 30,
    "difficulty": "hard",
    "knowledgePointIds": [],
    "practiceQuestionIds": [],
    "tags": [
      "SysDesign"
    ],
    "prerequisites": [],
    "updatedAt": "2026-07-03T00:00:00.000Z"
  },
  {
    "id": "sy-lesson-146",
    "courseId": "sy-course-12",
    "order": 3,
    "title": "SD课程12章3",
    "slug": "SD课程12章3",
    "summary": "SD课程12章3",
    "content": "# SD课程12章3\n\nSD课程12章3内容。",
    "contentFormat": "markdown",
    "estimatedMinutes": 30,
    "difficulty": "hard",
    "knowledgePointIds": [],
    "practiceQuestionIds": [],
    "tags": [
      "SysDesign"
    ],
    "prerequisites": [],
    "updatedAt": "2026-07-03T00:00:00.000Z"
  },
  {
    "id": "sy-lesson-147",
    "courseId": "sy-course-12",
    "order": 4,
    "title": "SD课程12章4",
    "slug": "SD课程12章4",
    "summary": "SD课程12章4",
    "content": "# SD课程12章4\n\nSD课程12章4内容。",
    "contentFormat": "markdown",
    "estimatedMinutes": 30,
    "difficulty": "hard",
    "knowledgePointIds": [],
    "practiceQuestionIds": [],
    "tags": [
      "SysDesign"
    ],
    "prerequisites": [],
    "updatedAt": "2026-07-03T00:00:00.000Z"
  },
  {
    "id": "sy-lesson-148",
    "courseId": "sy-course-12",
    "order": 5,
    "title": "SD课程12章5",
    "slug": "SD课程12章5",
    "summary": "SD课程12章5",
    "content": "# SD课程12章5\n\nSD课程12章5内容。",
    "contentFormat": "markdown",
    "estimatedMinutes": 30,
    "difficulty": "hard",
    "knowledgePointIds": [],
    "practiceQuestionIds": [],
    "tags": [
      "SysDesign"
    ],
    "prerequisites": [],
    "updatedAt": "2026-07-03T00:00:00.000Z"
  },
  {
    "id": "sy-lesson-149",
    "courseId": "sy-course-12",
    "order": 6,
    "title": "SD课程12章6",
    "slug": "SD课程12章6",
    "summary": "SD课程12章6",
    "content": "# SD课程12章6\n\nSD课程12章6内容。",
    "contentFormat": "markdown",
    "estimatedMinutes": 30,
    "difficulty": "hard",
    "knowledgePointIds": [],
    "practiceQuestionIds": [],
    "tags": [
      "SysDesign"
    ],
    "prerequisites": [],
    "updatedAt": "2026-07-03T00:00:00.000Z"
  },
  {
    "id": "sy-lesson-150",
    "courseId": "sy-course-12",
    "order": 7,
    "title": "SD课程12章7",
    "slug": "SD课程12章7",
    "summary": "SD课程12章7",
    "content": "# SD课程12章7\n\nSD课程12章7内容。",
    "contentFormat": "markdown",
    "estimatedMinutes": 30,
    "difficulty": "hard",
    "knowledgePointIds": [],
    "practiceQuestionIds": [],
    "tags": [
      "SysDesign"
    ],
    "prerequisites": [],
    "updatedAt": "2026-07-03T00:00:00.000Z"
  },
  {
    "id": "sy-lesson-151",
    "courseId": "sy-course-12",
    "order": 8,
    "title": "SD课程12章8",
    "slug": "SD课程12章8",
    "summary": "SD课程12章8",
    "content": "# SD课程12章8\n\nSD课程12章8内容。",
    "contentFormat": "markdown",
    "estimatedMinutes": 30,
    "difficulty": "hard",
    "knowledgePointIds": [],
    "practiceQuestionIds": [],
    "tags": [
      "SysDesign"
    ],
    "prerequisites": [],
    "updatedAt": "2026-07-03T00:00:00.000Z"
  },
  {
    "id": "sy-lesson-152",
    "courseId": "sy-course-12",
    "order": 9,
    "title": "SD课程12章9",
    "slug": "SD课程12章9",
    "summary": "SD课程12章9",
    "content": "# SD课程12章9\n\nSD课程12章9内容。",
    "contentFormat": "markdown",
    "estimatedMinutes": 30,
    "difficulty": "hard",
    "knowledgePointIds": [],
    "practiceQuestionIds": [],
    "tags": [
      "SysDesign"
    ],
    "prerequisites": [],
    "updatedAt": "2026-07-03T00:00:00.000Z"
  },
  {
    "id": "sy-lesson-153",
    "courseId": "sy-course-12",
    "order": 10,
    "title": "SD课程12章10",
    "slug": "SD课程12章10",
    "summary": "SD课程12章10",
    "content": "# SD课程12章10\n\nSD课程12章10内容。",
    "contentFormat": "markdown",
    "estimatedMinutes": 30,
    "difficulty": "hard",
    "knowledgePointIds": [],
    "practiceQuestionIds": [],
    "tags": [
      "SysDesign"
    ],
    "prerequisites": [],
    "updatedAt": "2026-07-03T00:00:00.000Z"
  },
  {
    "id": "sy-lesson-154",
    "courseId": "sy-course-12",
    "order": 11,
    "title": "SD课程12章11",
    "slug": "SD课程12章11",
    "summary": "SD课程12章11",
    "content": "# SD课程12章11\n\nSD课程12章11内容。",
    "contentFormat": "markdown",
    "estimatedMinutes": 30,
    "difficulty": "hard",
    "knowledgePointIds": [],
    "practiceQuestionIds": [],
    "tags": [
      "SysDesign"
    ],
    "prerequisites": [],
    "updatedAt": "2026-07-03T00:00:00.000Z"
  },
  {
    "id": "sy-lesson-155",
    "courseId": "sy-course-12",
    "order": 12,
    "title": "SD课程12章12",
    "slug": "SD课程12章12",
    "summary": "SD课程12章12",
    "content": "# SD课程12章12\n\nSD课程12章12内容。",
    "contentFormat": "markdown",
    "estimatedMinutes": 30,
    "difficulty": "hard",
    "knowledgePointIds": [],
    "practiceQuestionIds": [],
    "tags": [
      "SysDesign"
    ],
    "prerequisites": [],
    "updatedAt": "2026-07-03T00:00:00.000Z"
  },
  {
    "id": "sy-lesson-156",
    "courseId": "sy-course-12",
    "order": 13,
    "title": "SD课程12章13",
    "slug": "SD课程12章13",
    "summary": "SD课程12章13",
    "content": "# SD课程12章13\n\nSD课程12章13内容。",
    "contentFormat": "markdown",
    "estimatedMinutes": 30,
    "difficulty": "hard",
    "knowledgePointIds": [],
    "practiceQuestionIds": [],
    "tags": [
      "SysDesign"
    ],
    "prerequisites": [],
    "updatedAt": "2026-07-03T00:00:00.000Z"
  },
  {
    "id": "sy-lesson-157",
    "courseId": "sy-course-13",
    "order": 1,
    "title": "SD课程13章1",
    "slug": "SD课程13章1",
    "summary": "SD课程13章1",
    "content": "# SD课程13章1\n\nSD课程13章1内容。",
    "contentFormat": "markdown",
    "estimatedMinutes": 30,
    "difficulty": "hard",
    "knowledgePointIds": [],
    "practiceQuestionIds": [],
    "tags": [
      "SysDesign"
    ],
    "prerequisites": [],
    "updatedAt": "2026-07-03T00:00:00.000Z"
  },
  {
    "id": "sy-lesson-158",
    "courseId": "sy-course-13",
    "order": 2,
    "title": "SD课程13章2",
    "slug": "SD课程13章2",
    "summary": "SD课程13章2",
    "content": "# SD课程13章2\n\nSD课程13章2内容。",
    "contentFormat": "markdown",
    "estimatedMinutes": 30,
    "difficulty": "hard",
    "knowledgePointIds": [],
    "practiceQuestionIds": [],
    "tags": [
      "SysDesign"
    ],
    "prerequisites": [],
    "updatedAt": "2026-07-03T00:00:00.000Z"
  },
  {
    "id": "sy-lesson-159",
    "courseId": "sy-course-13",
    "order": 3,
    "title": "SD课程13章3",
    "slug": "SD课程13章3",
    "summary": "SD课程13章3",
    "content": "# SD课程13章3\n\nSD课程13章3内容。",
    "contentFormat": "markdown",
    "estimatedMinutes": 30,
    "difficulty": "hard",
    "knowledgePointIds": [],
    "practiceQuestionIds": [],
    "tags": [
      "SysDesign"
    ],
    "prerequisites": [],
    "updatedAt": "2026-07-03T00:00:00.000Z"
  },
  {
    "id": "sy-lesson-160",
    "courseId": "sy-course-13",
    "order": 4,
    "title": "SD课程13章4",
    "slug": "SD课程13章4",
    "summary": "SD课程13章4",
    "content": "# SD课程13章4\n\nSD课程13章4内容。",
    "contentFormat": "markdown",
    "estimatedMinutes": 30,
    "difficulty": "hard",
    "knowledgePointIds": [],
    "practiceQuestionIds": [],
    "tags": [
      "SysDesign"
    ],
    "prerequisites": [],
    "updatedAt": "2026-07-03T00:00:00.000Z"
  },
  {
    "id": "sy-lesson-161",
    "courseId": "sy-course-13",
    "order": 5,
    "title": "SD课程13章5",
    "slug": "SD课程13章5",
    "summary": "SD课程13章5",
    "content": "# SD课程13章5\n\nSD课程13章5内容。",
    "contentFormat": "markdown",
    "estimatedMinutes": 30,
    "difficulty": "hard",
    "knowledgePointIds": [],
    "practiceQuestionIds": [],
    "tags": [
      "SysDesign"
    ],
    "prerequisites": [],
    "updatedAt": "2026-07-03T00:00:00.000Z"
  },
  {
    "id": "sy-lesson-162",
    "courseId": "sy-course-13",
    "order": 6,
    "title": "SD课程13章6",
    "slug": "SD课程13章6",
    "summary": "SD课程13章6",
    "content": "# SD课程13章6\n\nSD课程13章6内容。",
    "contentFormat": "markdown",
    "estimatedMinutes": 30,
    "difficulty": "hard",
    "knowledgePointIds": [],
    "practiceQuestionIds": [],
    "tags": [
      "SysDesign"
    ],
    "prerequisites": [],
    "updatedAt": "2026-07-03T00:00:00.000Z"
  },
  {
    "id": "sy-lesson-163",
    "courseId": "sy-course-13",
    "order": 7,
    "title": "SD课程13章7",
    "slug": "SD课程13章7",
    "summary": "SD课程13章7",
    "content": "# SD课程13章7\n\nSD课程13章7内容。",
    "contentFormat": "markdown",
    "estimatedMinutes": 30,
    "difficulty": "hard",
    "knowledgePointIds": [],
    "practiceQuestionIds": [],
    "tags": [
      "SysDesign"
    ],
    "prerequisites": [],
    "updatedAt": "2026-07-03T00:00:00.000Z"
  },
  {
    "id": "sy-lesson-164",
    "courseId": "sy-course-13",
    "order": 8,
    "title": "SD课程13章8",
    "slug": "SD课程13章8",
    "summary": "SD课程13章8",
    "content": "# SD课程13章8\n\nSD课程13章8内容。",
    "contentFormat": "markdown",
    "estimatedMinutes": 30,
    "difficulty": "hard",
    "knowledgePointIds": [],
    "practiceQuestionIds": [],
    "tags": [
      "SysDesign"
    ],
    "prerequisites": [],
    "updatedAt": "2026-07-03T00:00:00.000Z"
  },
  {
    "id": "sy-lesson-165",
    "courseId": "sy-course-13",
    "order": 9,
    "title": "SD课程13章9",
    "slug": "SD课程13章9",
    "summary": "SD课程13章9",
    "content": "# SD课程13章9\n\nSD课程13章9内容。",
    "contentFormat": "markdown",
    "estimatedMinutes": 30,
    "difficulty": "hard",
    "knowledgePointIds": [],
    "practiceQuestionIds": [],
    "tags": [
      "SysDesign"
    ],
    "prerequisites": [],
    "updatedAt": "2026-07-03T00:00:00.000Z"
  },
  {
    "id": "sy-lesson-166",
    "courseId": "sy-course-13",
    "order": 10,
    "title": "SD课程13章10",
    "slug": "SD课程13章10",
    "summary": "SD课程13章10",
    "content": "# SD课程13章10\n\nSD课程13章10内容。",
    "contentFormat": "markdown",
    "estimatedMinutes": 30,
    "difficulty": "hard",
    "knowledgePointIds": [],
    "practiceQuestionIds": [],
    "tags": [
      "SysDesign"
    ],
    "prerequisites": [],
    "updatedAt": "2026-07-03T00:00:00.000Z"
  },
  {
    "id": "sy-lesson-167",
    "courseId": "sy-course-13",
    "order": 11,
    "title": "SD课程13章11",
    "slug": "SD课程13章11",
    "summary": "SD课程13章11",
    "content": "# SD课程13章11\n\nSD课程13章11内容。",
    "contentFormat": "markdown",
    "estimatedMinutes": 30,
    "difficulty": "hard",
    "knowledgePointIds": [],
    "practiceQuestionIds": [],
    "tags": [
      "SysDesign"
    ],
    "prerequisites": [],
    "updatedAt": "2026-07-03T00:00:00.000Z"
  },
  {
    "id": "sy-lesson-168",
    "courseId": "sy-course-13",
    "order": 12,
    "title": "SD课程13章12",
    "slug": "SD课程13章12",
    "summary": "SD课程13章12",
    "content": "# SD课程13章12\n\nSD课程13章12内容。",
    "contentFormat": "markdown",
    "estimatedMinutes": 30,
    "difficulty": "hard",
    "knowledgePointIds": [],
    "practiceQuestionIds": [],
    "tags": [
      "SysDesign"
    ],
    "prerequisites": [],
    "updatedAt": "2026-07-03T00:00:00.000Z"
  },
  {
    "id": "sy-lesson-169",
    "courseId": "sy-course-13",
    "order": 13,
    "title": "SD课程13章13",
    "slug": "SD课程13章13",
    "summary": "SD课程13章13",
    "content": "# SD课程13章13\n\nSD课程13章13内容。",
    "contentFormat": "markdown",
    "estimatedMinutes": 30,
    "difficulty": "hard",
    "knowledgePointIds": [],
    "practiceQuestionIds": [],
    "tags": [
      "SysDesign"
    ],
    "prerequisites": [],
    "updatedAt": "2026-07-03T00:00:00.000Z"
  },
  {
    "id": "sy-lesson-170",
    "courseId": "sy-course-14",
    "order": 1,
    "title": "SD课程14章1",
    "slug": "SD课程14章1",
    "summary": "SD课程14章1",
    "content": "# SD课程14章1\n\nSD课程14章1内容。",
    "contentFormat": "markdown",
    "estimatedMinutes": 30,
    "difficulty": "hard",
    "knowledgePointIds": [],
    "practiceQuestionIds": [],
    "tags": [
      "SysDesign"
    ],
    "prerequisites": [],
    "updatedAt": "2026-07-03T00:00:00.000Z"
  },
  {
    "id": "sy-lesson-171",
    "courseId": "sy-course-14",
    "order": 2,
    "title": "SD课程14章2",
    "slug": "SD课程14章2",
    "summary": "SD课程14章2",
    "content": "# SD课程14章2\n\nSD课程14章2内容。",
    "contentFormat": "markdown",
    "estimatedMinutes": 30,
    "difficulty": "hard",
    "knowledgePointIds": [],
    "practiceQuestionIds": [],
    "tags": [
      "SysDesign"
    ],
    "prerequisites": [],
    "updatedAt": "2026-07-03T00:00:00.000Z"
  },
  {
    "id": "sy-lesson-172",
    "courseId": "sy-course-14",
    "order": 3,
    "title": "SD课程14章3",
    "slug": "SD课程14章3",
    "summary": "SD课程14章3",
    "content": "# SD课程14章3\n\nSD课程14章3内容。",
    "contentFormat": "markdown",
    "estimatedMinutes": 30,
    "difficulty": "hard",
    "knowledgePointIds": [],
    "practiceQuestionIds": [],
    "tags": [
      "SysDesign"
    ],
    "prerequisites": [],
    "updatedAt": "2026-07-03T00:00:00.000Z"
  },
  {
    "id": "sy-lesson-173",
    "courseId": "sy-course-14",
    "order": 4,
    "title": "SD课程14章4",
    "slug": "SD课程14章4",
    "summary": "SD课程14章4",
    "content": "# SD课程14章4\n\nSD课程14章4内容。",
    "contentFormat": "markdown",
    "estimatedMinutes": 30,
    "difficulty": "hard",
    "knowledgePointIds": [],
    "practiceQuestionIds": [],
    "tags": [
      "SysDesign"
    ],
    "prerequisites": [],
    "updatedAt": "2026-07-03T00:00:00.000Z"
  },
  {
    "id": "sy-lesson-174",
    "courseId": "sy-course-14",
    "order": 5,
    "title": "SD课程14章5",
    "slug": "SD课程14章5",
    "summary": "SD课程14章5",
    "content": "# SD课程14章5\n\nSD课程14章5内容。",
    "contentFormat": "markdown",
    "estimatedMinutes": 30,
    "difficulty": "hard",
    "knowledgePointIds": [],
    "practiceQuestionIds": [],
    "tags": [
      "SysDesign"
    ],
    "prerequisites": [],
    "updatedAt": "2026-07-03T00:00:00.000Z"
  },
  {
    "id": "sy-lesson-175",
    "courseId": "sy-course-14",
    "order": 6,
    "title": "SD课程14章6",
    "slug": "SD课程14章6",
    "summary": "SD课程14章6",
    "content": "# SD课程14章6\n\nSD课程14章6内容。",
    "contentFormat": "markdown",
    "estimatedMinutes": 30,
    "difficulty": "hard",
    "knowledgePointIds": [],
    "practiceQuestionIds": [],
    "tags": [
      "SysDesign"
    ],
    "prerequisites": [],
    "updatedAt": "2026-07-03T00:00:00.000Z"
  },
  {
    "id": "sy-lesson-176",
    "courseId": "sy-course-14",
    "order": 7,
    "title": "SD课程14章7",
    "slug": "SD课程14章7",
    "summary": "SD课程14章7",
    "content": "# SD课程14章7\n\nSD课程14章7内容。",
    "contentFormat": "markdown",
    "estimatedMinutes": 30,
    "difficulty": "hard",
    "knowledgePointIds": [],
    "practiceQuestionIds": [],
    "tags": [
      "SysDesign"
    ],
    "prerequisites": [],
    "updatedAt": "2026-07-03T00:00:00.000Z"
  },
  {
    "id": "sy-lesson-177",
    "courseId": "sy-course-14",
    "order": 8,
    "title": "SD课程14章8",
    "slug": "SD课程14章8",
    "summary": "SD课程14章8",
    "content": "# SD课程14章8\n\nSD课程14章8内容。",
    "contentFormat": "markdown",
    "estimatedMinutes": 30,
    "difficulty": "hard",
    "knowledgePointIds": [],
    "practiceQuestionIds": [],
    "tags": [
      "SysDesign"
    ],
    "prerequisites": [],
    "updatedAt": "2026-07-03T00:00:00.000Z"
  },
  {
    "id": "sy-lesson-178",
    "courseId": "sy-course-14",
    "order": 9,
    "title": "SD课程14章9",
    "slug": "SD课程14章9",
    "summary": "SD课程14章9",
    "content": "# SD课程14章9\n\nSD课程14章9内容。",
    "contentFormat": "markdown",
    "estimatedMinutes": 30,
    "difficulty": "hard",
    "knowledgePointIds": [],
    "practiceQuestionIds": [],
    "tags": [
      "SysDesign"
    ],
    "prerequisites": [],
    "updatedAt": "2026-07-03T00:00:00.000Z"
  },
  {
    "id": "sy-lesson-179",
    "courseId": "sy-course-14",
    "order": 10,
    "title": "SD课程14章10",
    "slug": "SD课程14章10",
    "summary": "SD课程14章10",
    "content": "# SD课程14章10\n\nSD课程14章10内容。",
    "contentFormat": "markdown",
    "estimatedMinutes": 30,
    "difficulty": "hard",
    "knowledgePointIds": [],
    "practiceQuestionIds": [],
    "tags": [
      "SysDesign"
    ],
    "prerequisites": [],
    "updatedAt": "2026-07-03T00:00:00.000Z"
  },
  {
    "id": "sy-lesson-180",
    "courseId": "sy-course-14",
    "order": 11,
    "title": "SD课程14章11",
    "slug": "SD课程14章11",
    "summary": "SD课程14章11",
    "content": "# SD课程14章11\n\nSD课程14章11内容。",
    "contentFormat": "markdown",
    "estimatedMinutes": 30,
    "difficulty": "hard",
    "knowledgePointIds": [],
    "practiceQuestionIds": [],
    "tags": [
      "SysDesign"
    ],
    "prerequisites": [],
    "updatedAt": "2026-07-03T00:00:00.000Z"
  },
  {
    "id": "sy-lesson-181",
    "courseId": "sy-course-14",
    "order": 12,
    "title": "SD课程14章12",
    "slug": "SD课程14章12",
    "summary": "SD课程14章12",
    "content": "# SD课程14章12\n\nSD课程14章12内容。",
    "contentFormat": "markdown",
    "estimatedMinutes": 30,
    "difficulty": "hard",
    "knowledgePointIds": [],
    "practiceQuestionIds": [],
    "tags": [
      "SysDesign"
    ],
    "prerequisites": [],
    "updatedAt": "2026-07-03T00:00:00.000Z"
  },
  {
    "id": "sy-lesson-182",
    "courseId": "sy-course-14",
    "order": 13,
    "title": "SD课程14章13",
    "slug": "SD课程14章13",
    "summary": "SD课程14章13",
    "content": "# SD课程14章13\n\nSD课程14章13内容。",
    "contentFormat": "markdown",
    "estimatedMinutes": 30,
    "difficulty": "hard",
    "knowledgePointIds": [],
    "practiceQuestionIds": [],
    "tags": [
      "SysDesign"
    ],
    "prerequisites": [],
    "updatedAt": "2026-07-03T00:00:00.000Z"
  }
]